{
  "href": "https://api.spotify.com/v1/albums/5bLE2kmkZWlzAYeb6To6LA/tracks?offset=0&limit=50",
  "items": [
    {
      "artists": [
        {
          "external_urls": {
            "spotify": "https://open.spotify.com/artist/6eUKZXaKkcviH0Ku9w2n3V"
          },
          "href": "https://api.spotify.com/v1/artists/6eUKZXaKkcviH0Ku9w2n3V",
          "id": "6eUKZXaKkcviH0Ku9w2n3V",
          "name": "Ed Sheeran",
          "type": "artist",
          "uri": "spotify:artist:6eUKZXaKkcviH0Ku9w2n3V"
        }
      ],
      "available_markets": [
        "AR",
        "AU",
        "AT",
        "BE",
        "BO",
        "BR",
        "BG",
        "CA",
        "CL",
        "CO",
        "CR",
        "CY",
        "CZ",
        "DK",
        "DO",
        "DE",
        "EC",
        "EE",
        "SV",
        "FI",
        "FR",
        "GR",
        "GT",
        "HN",
        "HK",
        "HU",
        "IS",
        "IE",
        "IT",
        "LV",
        "LT",
        "LU",
        "MY",
        "MT",
        "MX",
        "NL",
        "NZ",
        "NI",
        "NO",
        "PA",
        "PY",
        "PE",
        "PH",
        "PL",
        "PT",
        "SG",
        "SK",
        "ES",
        "SE",
        "CH",
        "TW",
        "TR",
        "UY",
        "US",
        "GB",
        "AD",
        "LI",
        "MC",
        "ID",
        "JP",
        "TH",
        "VN",
        "RO",
        "IL",
        "ZA",
        "SA",
        "AE",
        "BH",
        "QA",
        "OM",
        "KW",
        "EG",
        "MA",
        "DZ",
        "TN",
        "LB",
        "JO",
        "PS",
        "IN",
        "KZ",
        "MD",
        "UA",
        "AL",
        "BA",
        "HR",
        "ME",
        "MK",
        "RS",
        "SI",
        "KR",
        "BD",
        "PK",
        "LK",
        "GH",
        "KE",
        "NG",
        "TZ",
        "UG",
        "AG",
        "AM",
        "BS",
        "BB",
        "BZ",
        "BT",
        "BW",
        "BF",
        "CV",
        "CW",
        "DM",
        "FJ",
        "GM",
        "GE",
        "GD",
        "GW",
        "GY",
        "HT",
        "JM",
        "KI",
        "LS",
        "LR",
        "MW",
        "MV",
        "ML",
        "MH",
        "FM",
        "NA",
        "NR",
        "NE",
        "PW",
        "PG",
        "PR",
        "WS",
        "SM",
        "ST",
        "SN",
        "SC",
        "SL",
        "SB",
        "KN",
        "LC",
        "VC",
        "SR",
        "TL",
        "TO",
        "TT",
        "TV",
        "VU",
        "AZ",
        "BN",
        "BI",
        "KH",
        "CM",
        "TD",
        "KM",
        "GQ",
        "SZ",
        "GA",
        "GN",
        "KG",
        "LA",
        "MO",
        "MR",
        "MN",
        "NP",
        "RW",
        "TG",
        "UZ",
        "ZW",
        "BJ",
        "MG",
        "MU",
        "MZ",
        "AO",
        "CI",
        "DJ",
        "ZM",
        "CD",
        "CG",
        "IQ",
        "LY",
        "TJ",
        "VE",
        "ET",
        "XK"
      ],
      "disc_number": 1,
      "duration_ms": 194277,
      "explicit": false,
      "external_urls": {
        "spotify": "https://open.spotify.com/track/0V0jxLGonu3pJV6hOl8CSK"
      },
      "href": "https://api.spotify.com/v1/tracks/0V0jxLGonu3pJV6hOl8CSK",
      "id": "0V0jxLGonu3pJV6hOl8CSK",
      "name": "Magical",
      "preview_url": null,
      "track_number": 1,
      "type": "track",
      "uri": "spotify:track:0V0jxLGonu3pJV6hOl8CSK",
      "is_local": false
    },
    {
      "artists": [
        {
          "external_urls": {
            "spotify": "https://open.spotify.com/artist/6eUKZXaKkcviH0Ku9w2n3V"
          },
          "href": "https://api.spotify.com/v1/artists/6eUKZXaKkcviH0Ku9w2n3V",
          "id": "6eUKZXaKkcviH0Ku9w2n3V",
          "name": "Ed Sheeran",
          "type": "artist",
          "uri": "spotify:artist:6eUKZXaKkcviH0Ku9w2n3V"
        }
      ],
      "available_markets": [
        "AR",
        "AU",
        "AT",
        "BE",
        "BO",
        "BR",
        "BG",
        "CA",
        "CL",
        "CO",
        "CR",
        "CY",
        "CZ",
        "DK",
        "DO",
        "DE",
        "EC",
        "EE",
        "SV",
        "FI",
        "FR",
        "GR",
        "GT",
        "HN",
        "HK",
        "HU",
        "IS",
        "IE",
        "IT",
        "LV",
        "LT",
        "LU",
        "MY",
        "MT",
        "MX",
        "NL",
        "NZ",
        "NI",
        "NO",
        "PA",
        "PY",
        "PE",
        "PH",
        "PL",
        "PT",
        "SG",
        "SK",
        "ES",
        "SE",
        "CH",
        "TW",
        "TR",
        "UY",
        "US",
        "GB",
        "AD",
        "LI",
        "MC",
        "ID",
        "JP",
        "TH",
        "VN",
        "RO",
        "IL",
        "ZA",
        "SA",
        "AE",
        "BH",
        "QA",
        "OM",
        "KW",
        "EG",
        "MA",
        "DZ",
        "TN",
        "LB",
        "JO",
        "PS",
        "IN",
        "KZ",
        "MD",
        "UA",
        "AL",
        "BA",
        "HR",
        "ME",
        "MK",
        "RS",
        "SI",
        "KR",
        "BD",
        "PK",
        "LK",
        "GH",
        "KE",
        "NG",
        "TZ",
        "UG",
        "AG",
        "AM",
        "BS",
        "BB",
        "BZ",
        "BT",
        "BW",
        "BF",
        "CV",
        "CW",
        "DM",
        "FJ",
        "GM",
        "GE",
        "GD",
        "GW",
        "GY",
        "HT",
        "JM",
        "KI",
        "LS",
        "LR",
        "MW",
        "MV",
        "ML",
        "MH",
        "FM",
        "NA",
        "NR",
        "NE",
        "PW",
        "PG",
        "PR",
        "WS",
        "SM",
        "ST",
        "SN",
        "SC",
        "SL",
        "SB",
        "KN",
        "LC",
        "VC",
        "SR",
        "TL",
        "TO",
        "TT",
        "TV",
        "VU",
        "AZ",
        "BN",
        "BI",
        "KH",
        "CM",
        "TD",
        "KM",
        "GQ",
        "SZ",
        "GA",
        "GN",
        "KG",
        "LA",
        "MO",
        "MR",
        "MN",
        "NP",
        "RW",
        "TG",
        "UZ",
        "ZW",
        "BJ",
        "MG",
        "MU",
        "MZ",
        "AO",
        "CI",
        "DJ",
        "ZM",
        "CD",
        "CG",
        "IQ",
        "LY",
        "TJ",
        "VE",
        "ET",
        "XK"
      ],
      "disc_number": 1,
      "duration_ms": 226756,
      "explicit": false,
      "external_urls": {
        "spotify": "https://open.spotify.com/track/4OZoyD5m8Mrc0CMsAxBCU6"
      },
      "href": "https://api.spotify.com/v1/tracks/4OZoyD5m8Mrc0CMsAxBCU6",
      "id": "4OZoyD5m8Mrc0CMsAxBCU6",
      "name": "England",
      "preview_url": null,
      "track_number": 2,
      "type": "track",
      "uri": "spotify:track:4OZoyD5m8Mrc0CMsAxBCU6",
      "is_local": false
    },
    {
      "artists": [
        {
          "external_urls": {
            "spotify": "https://open.spotify.com/artist/6eUKZXaKkcviH0Ku9w2n3V"
          },
          "href": "https://api.spotify.com/v1/artists/6eUKZXaKkcviH0Ku9w2n3V",
          "id": "6eUKZXaKkcviH0Ku9w2n3V",
          "name": "Ed Sheeran",
          "type": "artist",
          "uri": "spotify:artist:6eUKZXaKkcviH0Ku9w2n3V"
        }
      ],
      "available_markets": [
        "AR",
        "AU",
        "AT",
        "BE",
        "BO",
        "BR",
        "BG",
        "CA",
        "CL",
        "CO",
        "CR",
        "CY",
        "CZ",
        "DK",
        "DO",
        "DE",
        "EC",
        "EE",
        "SV",
        "FI",
        "FR",
        "GR",
        "GT",
        "HN",
        "HK",
        "HU",
        "IS",
        "IE",
        "IT",
        "LV",
        "LT",
        "LU",
        "MY",
        "MT",
        "MX",
        "NL",
        "NZ",
        "NI",
        "NO",
        "PA",
        "PY",
        "PE",
        "PH",
        "PL",
        "PT",
        "SG",
        "SK",
        "ES",
        "SE",
        "CH",
        "TW",
        "TR",
        "UY",
        "US",
        "GB",
        "AD",
        "LI",
        "MC",
        "ID",
        "JP",
        "TH",
        "VN",
        "RO",
        "IL",
        "ZA",
        "SA",
        "AE",
        "BH",
        "QA",
        "OM",
        "KW",
        "EG",
        "MA",
        "DZ",
        "TN",
        "LB",
        "JO",
        "PS",
        "IN",
        "KZ",
        "MD",
        "UA",
        "AL",
        "BA",
        "HR",
        "ME",
        "MK",
        "RS",
        "SI",
        "KR",
        "BD",
        "PK",
        "LK",
        "GH",
        "KE",
        "NG",
        "TZ",
        "UG",
        "AG",
        "AM",
        "BS",
        "BB",
        "BZ",
        "BT",
        "BW",
        "BF",
        "CV",
        "CW",
        "DM",
        "FJ",
        "GM",
        "GE",
        "GD",
        "GW",
        "GY",
        "HT",
        "JM",
        "KI",
        "LS",
        "LR",
        "MW",
        "MV",
        "ML",
        "MH",
        "FM",
        "NA",
        "NR",
        "NE",
        "PW",
        "PG",
        "PR",
        "WS",
        "SM",
        "ST",
        "SN",
        "SC",
        "SL",
        "SB",
        "KN",
        "LC",
        "VC",
        "SR",
        "TL",
        "TO",
        "TT",
        "TV",
        "VU",
        "AZ",
        "BN",
        "BI",
        "KH",
        "CM",
        "TD",
        "KM",
        "GQ",
        "SZ",
        "GA",
        "GN",
        "KG",
        "LA",
        "MO",
        "MR",
        "MN",
        "NP",
        "RW",
        "TG",
        "UZ",
        "ZW",
        "BJ",
        "MG",
        "MU",
        "MZ",
        "AO",
        "CI",
        "DJ",
        "ZM",
        "CD",
        "CG",
        "IQ",
        "LY",
        "TJ",
        "VE",
        "ET",
        "XK"
      ],
      "disc_number": 1,
      "duration_ms": 245813,
      "explicit": false,
      "external_urls": {
        "spotify": "https://open.spotify.com/track/6rVxvys4tcXsNuw2xoKsLl"
      },
      "href": "https://api.spotify.com/v1/tracks/6rVxvys4tcXsNuw2xoKsLl",
      "id": "6rVxvys4tcXsNuw2xoKsLl",
      "name": "Amazing",
      "preview_url": null,
      "track_number": 3,
      "type": "track",
      "uri": "spotify:track:6rVxvys4tcXsNuw2xoKsLl",
      "is_local": false
    },
    {
      "artists": [
        {
          "external_urls": {
            "spotify": "https://open.spotify.com/artist/6eUKZXaKkcviH0Ku9w2n3V"
          },
          "href": "https://api.spotify.com/v1/artists/6eUKZXaKkcviH0Ku9w2n3V",
          "id": "6eUKZXaKkcviH0Ku9w2n3V",
          "name": "Ed Sheeran",
          "type": "artist",
          "uri": "spotify:artist:6eUKZXaKkcviH0Ku9w2n3V"
        }
      ],
      "available_markets": [
        "AR",
        "AU",
        "AT",
        "BE",
        "BO",
        "BR",
        "BG",
        "CA",
        "CL",
        "CO",
        "CR",
        "CY",
        "CZ",
        "DK",
        "DO",
        "DE",
        "EC",
        "EE",
        "SV",
        "FI",
        "FR",
        "GR",
        "GT",
        "HN",
        "HK",
        "HU",
        "IS",
        "IE",
        "IT",
        "LV",
        "LT",
        "LU",
        "MY",
        "MT",
        "MX",
        "NL",
        "NZ",
        "NI",
        "NO",
        "PA",
        "PY",
        "PE",
        "PH",
        "PL",
        "PT",
        "SG",
        "SK",
        "ES",
        "SE",
        "CH",
        "TW",
        "TR",
        "UY",
        "US",
        "GB",
        "AD",
        "LI",
        "MC",
        "ID",
        "JP",
        "TH",
        "VN",
        "RO",
        "IL",
        "ZA",
        "SA",
        "AE",
        "BH",
        "QA",
        "OM",
        "KW",
        "EG",
        "MA",
        "DZ",
        "TN",
        "LB",
        "JO",
        "PS",
        "IN",
        "KZ",
        "MD",
        "UA",
        "AL",
        "BA",
        "HR",
        "ME",
        "MK",
        "RS",
        "SI",
        "KR",
        "BD",
        "PK",
        "LK",
        "GH",
        "KE",
        "NG",
        "TZ",
        "UG",
        "AG",
        "AM",
        "BS",
        "BB",
        "BZ",
        "BT",
        "BW",
        "BF",
        "CV",
        "CW",
        "DM",
        "FJ",
        "GM",
        "GE",
        "GD",
        "GW",
        "GY",
        "HT",
        "JM",
        "KI",
        "LS",
        "LR",
        "MW",
        "MV",
        "ML",
        "MH",
        "FM",
        "NA",
        "NR",
        "NE",
        "PW",
        "PG",
        "PR",
        "WS",
        "SM",
        "ST",
        "SN",
        "SC",
        "SL",
        "SB",
        "KN",
        "LC",
        "VC",
        "SR",
        "TL",
        "TO",
        "TT",
        "TV",
        "VU",
        "AZ",
        "BN",
        "BI",
        "KH",
        "CM",
        "TD",
        "KM",
        "GQ",
        "SZ",
        "GA",
        "GN",
        "KG",
        "LA",
        "MO",
        "MR",
        "MN",
        "NP",
        "RW",
        "TG",
        "UZ",
        "ZW",
        "BJ",
        "MG",
        "MU",
        "MZ",
        "AO",
        "CI",
        "DJ",
        "ZM",
        "CD",
        "CG",
        "IQ",
        "LY",
        "TJ",
        "VE",
        "ET",
        "XK"
      ],
      "disc_number": 1,
      "duration_ms": 229850,
      "explicit": true,
      "external_urls": {
        "spotify": "https://open.spotify.com/track/11osH1qPIktZAVxjRd8EnW"
      },
      "href": "https://api.spotify.com/v1/tracks/11osH1qPIktZAVxjRd8EnW",
      "id": "11osH1qPIktZAVxjRd8EnW",
      "name": "Plastic Bag",
      "preview_url": null,
      "track_number": 4,
      "type": "track",
      "uri": "spotify:track:11osH1qPIktZAVxjRd8EnW",
      "is_local": false
    },
    {
      "artists": [
        {
          "external_urls": {
            "spotify": "https://open.spotify.com/artist/6eUKZXaKkcviH0Ku9w2n3V"
          },
          "href": "https://api.spotify.com/v1/artists/6eUKZXaKkcviH0Ku9w2n3V",
          "id": "6eUKZXaKkcviH0Ku9w2n3V",
          "name": "Ed Sheeran",
          "type": "artist",
          "uri": "spotify:artist:6eUKZXaKkcviH0Ku9w2n3V"
        }
      ],
      "available_markets": [
        "AR",
        "AU",
        "AT",
        "BE",
        "BO",
        "BR",
        "BG",
        "CA",
        "CL",
        "CO",
        "CR",
        "CY",
        "CZ",
        "DK",
        "DO",
        "DE",
        "EC",
        "EE",
        "SV",
        "FI",
        "FR",
        "GR",
        "GT",
        "HN",
        "HK",
        "HU",
        "IS",
        "IE",
        "IT",
        "LV",
        "LT",
        "LU",
        "MY",
        "MT",
        "MX",
        "NL",
        "NZ",
        "NI",
        "NO",
        "PA",
        "PY",
        "PE",
        "PH",
        "PL",
        "PT",
        "SG",
        "SK",
        "ES",
        "SE",
        "CH",
        "TW",
        "TR",
        "UY",
        "US",
        "GB",
        "AD",
        "LI",
        "MC",
        "ID",
        "JP",
        "TH",
        "VN",
        "RO",
        "IL",
        "ZA",
        "SA",
        "AE",
        "BH",
        "QA",
        "OM",
        "KW",
        "EG",
        "MA",
        "DZ",
        "TN",
        "LB",
        "JO",
        "PS",
        "IN",
        "KZ",
        "MD",
        "UA",
        "AL",
        "BA",
        "HR",
        "ME",
        "MK",
        "RS",
        "SI",
        "KR",
        "BD",
        "PK",
        "LK",
        "GH",
        "KE",
        "NG",
        "TZ",
        "UG",
        "AG",
        "AM",
        "BS",
        "BB",
        "BZ",
        "BT",
        "BW",
        "BF",
        "CV",
        "CW",
        "DM",
        "FJ",
        "GM",
        "GE",
        "GD",
        "GW",
        "GY",
        "HT",
        "JM",
        "KI",
        "LS",
        "LR",
        "MW",
        "MV",
        "ML",
        "MH",
        "FM",
        "NA",
        "NR",
        "NE",
        "PW",
        "PG",
        "PR",
        "WS",
        "SM",
        "ST",
        "SN",
        "SC",
        "SL",
        "SB",
        "KN",
        "LC",
        "VC",
        "SR",
        "TL",
        "TO",
        "TT",
        "TV",
        "VU",
        "AZ",
        "BN",
        "BI",
        "KH",
        "CM",
        "TD",
        "KM",
        "GQ",
        "SZ",
        "GA",
        "GN",
        "KG",
        "LA",
        "MO",
        "MR",
        "MN",
        "NP",
        "RW",
        "TG",
        "UZ",
        "ZW",
        "BJ",
        "MG",
        "MU",
        "MZ",
        "AO",
        "CI",
        "DJ",
        "ZM",
        "CD",
        "CG",
        "IQ",
        "LY",
        "TJ",
        "VE",
        "ET",
        "XK"
      ],
      "disc_number": 1,
      "duration_ms": 153899,
      "explicit": false,
      "external_urls": {
        "spotify": "https://open.spotify.com/track/4MIe9vXY61PuUeFSq1x8rM"
      },
      "href": "https://api.spotify.com/v1/tracks/4MIe9vXY61PuUeFSq1x8rM",
      "id": "4MIe9vXY61PuUeFSq1x8rM",
      "name": "Blue",
      "preview_url": null,
      "track_number": 5,
      "type": "track",
      "uri": "spotify:track:4MIe9vXY61PuUeFSq1x8rM",
      "is_local": false
    },
    {
      "artists": [
        {
          "external_urls": {
            "spotify": "https://open.spotify.com/artist/6eUKZXaKkcviH0Ku9w2n3V"
          },
          "href": "https://api.spotify.com/v1/artists/6eUKZXaKkcviH0Ku9w2n3V",
          "id": "6eUKZXaKkcviH0Ku9w2n3V",
          "name": "Ed Sheeran",
          "type": "artist",
          "uri": "spotify:artist:6eUKZXaKkcviH0Ku9w2n3V"
        }
      ],
      "available_markets": [
        "AR",
        "AU",
        "AT",
        "BE",
        "BO",
        "BR",
        "BG",
        "CA",
        "CL",
        "CO",
        "CR",
        "CY",
        "CZ",
        "DK",
        "DO",
        "DE",
        "EC",
        "EE",
        "SV",
        "FI",
        "FR",
        "GR",
        "GT",
        "HN",
        "HK",
        "HU",
        "IS",
        "IE",
        "IT",
        "LV",
        "LT",
        "LU",
        "MY",
        "MT",
        "MX",
        "NL",
        "NZ",
        "NI",
        "NO",
        "PA",
        "PY",
        "PE",
        "PH",
        "PL",
        "PT",
        "SG",
        "SK",
        "ES",
        "SE",
        "CH",
        "TW",
        "TR",
        "UY",
        "US",
        "GB",
        "AD",
        "LI",
        "MC",
        "ID",
        "JP",
        "TH",
        "VN",
        "RO",
        "IL",
        "ZA",
        "SA",
        "AE",
        "BH",
        "QA",
        "OM",
        "KW",
        "EG",
        "MA",
        "DZ",
        "TN",
        "LB",
        "JO",
        "PS",
        "IN",
        "KZ",
        "MD",
        "UA",
        "AL",
        "BA",
        "HR",
        "ME",
        "MK",
        "RS",
        "SI",
        "KR",
        "BD",
        "PK",
        "LK",
        "GH",
        "KE",
        "NG",
        "TZ",
        "UG",
        "AG",
        "AM",
        "BS",
        "BB",
        "BZ",
        "BT",
        "BW",
        "BF",
        "CV",
        "CW",
        "DM",
        "FJ",
        "GM",
        "GE",
        "GD",
        "GW",
        "GY",
        "HT",
        "JM",
        "KI",
        "LS",
        "LR",
        "MW",
        "MV",
        "ML",
        "MH",
        "FM",
        "NA",
        "NR",
        "NE",
        "PW",
        "PG",
        "PR",
        "WS",
        "SM",
        "ST",
        "SN",
        "SC",
        "SL",
        "SB",
        "KN",
        "LC",
        "VC",
        "SR",
        "TL",
        "TO",
        "TT",
        "TV",
        "VU",
        "AZ",
        "BN",
        "BI",
        "KH",
        "CM",
        "TD",
        "KM",
        "GQ",
        "SZ",
        "GA",
        "GN",
        "KG",
        "LA",
        "MO",
        "MR",
        "MN",
        "NP",
        "RW",
        "TG",
        "UZ",
        "ZW",
        "BJ",
        "MG",
        "MU",
        "MZ",
        "AO",
        "CI",
        "DJ",
        "ZM",
        "CD",
        "CG",
        "IQ",
        "LY",
        "TJ",
        "VE",
        "ET",
        "XK"
      ],
      "disc_number": 1,
      "duration_ms": 197976,
      "explicit": false,
      "external_urls": {
        "spotify": "https://open.spotify.com/track/58oljhgRB2FFtF1l2v31QJ"
      },
      "href": "https://api.spotify.com/v1/tracks/58oljhgRB2FFtF1l2v31QJ",
      "id": "58oljhgRB2FFtF1l2v31QJ",
      "name": "American Town",
      "preview_url": null,
      "track_number": 6,
      "type": "track",
      "uri": "spotify:track:58oljhgRB2FFtF1l2v31QJ",
      "is_local": false
    },
    {
      "artists": [
        {
          "external_urls": {
            "spotify": "https://open.spotify.com/artist/6eUKZXaKkcviH0Ku9w2n3V"
          },
          "href": "https://api.spotify.com/v1/artists/6eUKZXaKkcviH0Ku9w2n3V",
          "id": "6eUKZXaKkcviH0Ku9w2n3V",
          "name": "Ed Sheeran",
          "type": "artist",
          "uri": "spotify:artist:6eUKZXaKkcviH0Ku9w2n3V"
        }
      ],
      "available_markets": [
        "AR",
        "AU",
        "AT",
        "BE",
        "BO",
        "BR",
        "BG",
        "CA",
        "CL",
        "CO",
        "CR",
        "CY",
        "CZ",
        "DK",
        "DO",
        "DE",
        "EC",
        "EE",
        "SV",
        "FI",
        "FR",
        "GR",
        "GT",
        "HN",
        "HK",
        "HU",
        "IS",
        "IE",
        "IT",
        "LV",
        "LT",
        "LU",
        "MY",
        "MT",
        "MX",
        "NL",
        "NZ",
        "NI",
        "NO",
        "PA",
        "PY",
        "PE",
        "PH",
        "PL",
        "PT",
        "SG",
        "SK",
        "ES",
        "SE",
        "CH",
        "TW",
        "TR",
        "UY",
        "US",
        "GB",
        "AD",
        "LI",
        "MC",
        "ID",
        "JP",
        "TH",
        "VN",
        "RO",
        "IL",
        "ZA",
        "SA",
        "AE",
        "BH",
        "QA",
        "OM",
        "KW",
        "EG",
        "MA",
        "DZ",
        "TN",
        "LB",
        "JO",
        "PS",
        "IN",
        "KZ",
        "MD",
        "UA",
        "AL",
        "BA",
        "HR",
        "ME",
        "MK",
        "RS",
        "SI",
        "KR",
        "BD",
        "PK",
        "LK",
        "GH",
        "KE",
        "NG",
        "TZ",
        "UG",
        "AG",
        "AM",
        "BS",
        "BB",
        "BZ",
        "BT",
        "BW",
        "BF",
        "CV",
        "CW",
        "DM",
        "FJ",
        "GM",
        "GE",
        "GD",
        "GW",
        "GY",
        "HT",
        "JM",
        "KI",
        "LS",
        "LR",
        "MW",
        "MV",
        "ML",
        "MH",
        "FM",
        "NA",
        "NR",
        "NE",
        "PW",
        "PG",
        "PR",
        "WS",
        "SM",
        "ST",
        "SN",
        "SC",
        "SL",
        "SB",
        "KN",
        "LC",
        "VC",
        "SR",
        "TL",
        "TO",
        "TT",
        "TV",
        "VU",
        "AZ",
        "BN",
        "BI",
        "KH",
        "CM",
        "TD",
        "KM",
        "GQ",
        "SZ",
        "GA",
        "GN",
        "KG",
        "LA",
        "MO",
        "MR",
        "MN",
        "NP",
        "RW",
        "TG",
        "UZ",
        "ZW",
        "BJ",
        "MG",
        "MU",
        "MZ",
        "AO",
        "CI",
        "DJ",
        "ZM",
        "CD",
        "CG",
        "IQ",
        "LY",
        "TJ",
        "VE",
        "ET",
        "XK"
      ],
      "disc_number": 1,
      "duration_ms": 227398,
      "explicit": true,
      "external_urls": {
        "spotify": "https://open.spotify.com/track/4W8EmeDnNxqRXEeVSpHDn7"
      },
      "href": "https://api.spotify.com/v1/tracks/4W8EmeDnNxqRXEeVSpHDn7",
      "id": "4W8EmeDnNxqRXEeVSpHDn7",
      "name": "That’s On Me",
      "preview_url": null,
      "track_number": 7,
      "type": "track",
      "uri": "spotify:track:4W8EmeDnNxqRXEeVSpHDn7",
      "is_local": false
    },
    {
      "artists": [
        {
          "external_urls": {
            "spotify": "https://open.spotify.com/artist/6eUKZXaKkcviH0Ku9w2n3V"
          },
          "href": "https://api.spotify.com/v1/artists/6eUKZXaKkcviH0Ku9w2n3V",
          "id": "6eUKZXaKkcviH0Ku9w2n3V",
          "name": "Ed Sheeran",
          "type": "artist",
          "uri": "spotify:artist:6eUKZXaKkcviH0Ku9w2n3V"
        }
      ],
      "available_markets": [
        "AR",
        "AU",
        "AT",
        "BE",
        "BO",
        "BR",
        "BG",
        "CA",
        "CL",
        "CO",
        "CR",
        "CY",
        "CZ",
        "DK",
        "DO",
        "DE",
        "EC",
        "EE",
        "SV",
        "FI",
        "FR",
        "GR",
        "GT",
        "HN",
        "HK",
        "HU",
        "IS",
        "IE",
        "IT",
        "LV",
        "LT",
        "LU",
        "MY",
        "MT",
        "MX",
        "NL",
        "NZ",
        "NI",
        "NO",
        "PA",
        "PY",
        "PE",
        "PH",
        "PL",
        "PT",
        "SG",
        "SK",
        "ES",
        "SE",
        "CH",
        "TW",
        "TR",
        "UY",
        "US",
        "GB",
        "AD",
        "LI",
        "MC",
        "ID",
        "JP",
        "TH",
        "VN",
        "RO",
        "IL",
        "ZA",
        "SA",
        "AE",
        "BH",
        "QA",
        "OM",
        "KW",
        "EG",
        "MA",
        "DZ",
        "TN",
        "LB",
        "JO",
        "PS",
        "IN",
        "KZ",
        "MD",
        "UA",
        "AL",
        "BA",
        "HR",
        "ME",
        "MK",
        "RS",
        "SI",
        "KR",
        "BD",
        "PK",
        "LK",
        "GH",
        "KE",
        "NG",
        "TZ",
        "UG",
        "AG",
        "AM",
        "BS",
        "BB",
        "BZ",
        "BT",
        "BW",
        "BF",
        "CV",
        "CW",
        "DM",
        "FJ",
        "GM",
        "GE",
        "GD",
        "GW",
        "GY",
        "HT",
        "JM",
        "KI",
        "LS",
        "LR",
        "MW",
        "MV",
        "ML",
        "MH",
        "FM",
        "NA",
        "NR",
        "NE",
        "PW",
        "PG",
        "PR",
        "WS",
        "SM",
        "ST",
        "SN",
        "SC",
        "SL",
        "SB",
        "KN",
        "LC",
        "VC",
        "SR",
        "TL",
        "TO",
        "TT",
        "TV",
        "VU",
        "AZ",
        "BN",
        "BI",
        "KH",
        "CM",
        "TD",
        "KM",
        "GQ",
        "SZ",
        "GA",
        "GN",
        "KG",
        "LA",
        "MO",
        "MR",
        "MN",
        "NP",
        "RW",
        "TG",
        "UZ",
        "ZW",
        "BJ",
        "MG",
        "MU",
        "MZ",
        "AO",
        "CI",
        "DJ",
        "ZM",
        "CD",
        "CG",
        "IQ",
        "LY",
        "TJ",
        "VE",
        "ET",
        "XK"
      ],
      "disc_number": 1,
      "duration_ms": 231021,
      "explicit": false,
      "external_urls": {
        "spotify": "https://open.spotify.com/track/3pBpGx6jM4cQGzn1EMx963"
      },
      "href": "https://api.spotify.com/v1/tracks/3pBpGx6jM4cQGzn1EMx963",
      "id": "3pBpGx6jM4cQGzn1EMx963",
      "name": "Page",
      "preview_url": null,
      "track_number": 8,
      "type": "track",
      "uri": "spotify:track:3pBpGx6jM4cQGzn1EMx963",
      "is_local": false
    },
    {
      "artists": [
        {
          "external_urls": {
            "spotify": "https://open.spotify.com/artist/6eUKZXaKkcviH0Ku9w2n3V"
          },
          "href": "https://api.spotify.com/v1/artists/6eUKZXaKkcviH0Ku9w2n3V",
          "id": "6eUKZXaKkcviH0Ku9w2n3V",
          "name": "Ed Sheeran",
          "type": "artist",
          "uri": "spotify:artist:6eUKZXaKkcviH0Ku9w2n3V"
        }
      ],
      "available_markets": [
        "AR",
        "AU",
        "AT",
        "BE",
        "BO",
        "BR",
        "BG",
        "CA",
        "CL",
        "CO",
        "CR",
        "CY",
        "CZ",
        "DK",
        "DO",
        "DE",
        "EC",
        "EE",
        "SV",
        "FI",
        "FR",
        "GR",
        "GT",
        "HN",
        "HK",
        "HU",
        "IS",
        "IE",
        "IT",
        "LV",
        "LT",
        "LU",
        "MY",
        "MT",
        "MX",
        "NL",
        "NZ",
        "NI",
        "NO",
        "PA",
        "PY",
        "PE",
        "PH",
        "PL",
        "PT",
        "SG",
        "SK",
        "ES",
        "SE",
        "CH",
        "TW",
        "TR",
        "UY",
        "US",
        "GB",
        "AD",
        "LI",
        "MC",
        "ID",
        "JP",
        "TH",
        "VN",
        "RO",
        "IL",
        "ZA",
        "SA",
        "AE",
        "BH",
        "QA",
        "OM",
        "KW",
        "EG",
        "MA",
        "DZ",
        "TN",
        "LB",
        "JO",
        "PS",
        "IN",
        "KZ",
        "MD",
        "UA",
        "AL",
        "BA",
        "HR",
        "ME",
        "MK",
        "RS",
        "SI",
        "KR",
        "BD",
        "PK",
        "LK",
        "GH",
        "KE",
        "NG",
        "TZ",
        "UG",
        "AG",
        "AM",
        "BS",
        "BB",
        "BZ",
        "BT",
        "BW",
        "BF",
        "CV",
        "CW",
        "DM",
        "FJ",
        "GM",
        "GE",
        "GD",
        "GW",
        "GY",
        "HT",
        "JM",
        "KI",
        "LS",
        "LR",
        "MW",
        "MV",
        "ML",
        "MH",
        "FM",
        "NA",
        "NR",
        "NE",
        "PW",
        "PG",
        "PR",
        "WS",
        "SM",
        "ST",
        "SN",
        "SC",
        "SL",
        "SB",
        "KN",
        "LC",
        "VC",
        "SR",
        "TL",
        "TO",
        "TT",
        "TV",
        "VU",
        "AZ",
        "BN",
        "BI",
        "KH",
        "CM",
        "TD",
        "KM",
        "GQ",
        "SZ",
        "GA",
        "GN",
        "KG",
        "LA",
        "MO",
        "MR",
        "MN",
        "NP",
        "RW",
        "TG",
        "UZ",
        "ZW",
        "BJ",
        "MG",
        "MU",
        "MZ",
        "AO",
        "CI",
        "DJ",
        "ZM",
        "CD",
        "CG",
        "IQ",
        "LY",
        "TJ",
        "VE",
        "ET",
        "XK"
      ],
      "disc_number": 1,
      "duration_ms": 179538,
      "explicit": false,
      "external_urls": {
        "spotify": "https://open.spotify.com/track/36TfNKDK3IuTC6E3UmfZ20"
      },
      "href": "https://api.spotify.com/v1/tracks/36TfNKDK3IuTC6E3UmfZ20",
      "id": "36TfNKDK3IuTC6E3UmfZ20",
      "name": "Midnight",
      "preview_url": null,
      "track_number": 9,
      "type": "track",
      "uri": "spotify:track:36TfNKDK3IuTC6E3UmfZ20",
      "is_local": false
    },
    {
      "artists": [
        {
          "external_urls": {
            "spotify": "https://open.spotify.com/artist/6eUKZXaKkcviH0Ku9w2n3V"
          },
          "href": "https://api.spotify.com/v1/artists/6eUKZXaKkcviH0Ku9w2n3V",
          "id": "6eUKZXaKkcviH0Ku9w2n3V",
          "name": "Ed Sheeran",
          "type": "artist",
          "uri": "spotify:artist:6eUKZXaKkcviH0Ku9w2n3V"
        }
      ],
      "available_markets": [
        "AR",
        "AU",
        "AT",
        "BE",
        "BO",
        "BR",
        "BG",
        "CA",
        "CL",
        "CO",
        "CR",
        "CY",
        "CZ",
        "DK",
        "DO",
        "DE",
        "EC",
        "EE",
        "SV",
        "FI",
        "FR",
        "GR",
        "GT",
        "HN",
        "HK",
        "HU",
        "IS",
        "IE",
        "IT",
        "LV",
        "LT",
        "LU",
        "MY",
        "MT",
        "MX",
        "NL",
        "NZ",
        "NI",
        "NO",
        "PA",
        "PY",
        "PE",
        "PH",
        "PL",
        "PT",
        "SG",
        "SK",
        "ES",
        "SE",
        "CH",
        "TW",
        "TR",
        "UY",
        "US",
        "GB",
        "AD",
        "LI",
        "MC",
        "ID",
        "JP",
        "TH",
        "VN",
        "RO",
        "IL",
        "ZA",
        "SA",
        "AE",
        "BH",
        "QA",
        "OM",
        "KW",
        "EG",
        "MA",
        "DZ",
        "TN",
        "LB",
        "JO",
        "PS",
        "IN",
        "KZ",
        "MD",
        "UA",
        "AL",
        "BA",
        "HR",
        "ME",
        "MK",
        "RS",
        "SI",
        "KR",
        "BD",
        "PK",
        "LK",
        "GH",
        "KE",
        "NG",
        "TZ",
        "UG",
        "AG",
        "AM",
        "BS",
        "BB",
        "BZ",
        "BT",
        "BW",
        "BF",
        "CV",
        "CW",
        "DM",
        "FJ",
        "GM",
        "GE",
        "GD",
        "GW",
        "GY",
        "HT",
        "JM",
        "KI",
        "LS",
        "LR",
        "MW",
        "MV",
        "ML",
        "MH",
        "FM",
        "NA",
        "NR",
        "NE",
        "PW",
        "PG",
        "PR",
        "WS",
        "SM",
        "ST",
        "SN",
        "SC",
        "SL",
        "SB",
        "KN",
        "LC",
        "VC",
        "SR",
        "TL",
        "TO",
        "TT",
        "TV",
        "VU",
        "AZ",
        "BN",
        "BI",
        "KH",
        "CM",
        "TD",
        "KM",
        "GQ",
        "SZ",
        "GA",
        "GN",
        "KG",
        "LA",
        "MO",
        "MR",
        "MN",
        "NP",
        "RW",
        "TG",
        "UZ",
        "ZW",
        "BJ",
        "MG",
        "MU",
        "MZ",
        "AO",
        "CI",
        "DJ",
        "ZM",
        "CD",
        "CG",
        "IQ",
        "LY",
        "TJ",
        "VE",
        "ET",
        "XK"
      ],
      "disc_number": 1,
      "duration_ms": 178615,
      "explicit": false,
      "external_urls": {
        "spotify": "https://open.spotify.com/track/4JV6AhDromrfPIVXuzEijV"
      },
      "href": "https://api.spotify.com/v1/tracks/4JV6AhDromrfPIVXuzEijV",
      "id": "4JV6AhDromrfPIVXuzEijV",
      "name": "Spring",
      "preview_url": null,
      "track_number": 10,
      "type": "track",
      "uri": "spotify:track:4JV6AhDromrfPIVXuzEijV",
      "is_local": false
    },
    {
      "artists": [
        {
          "external_urls": {
            "spotify": "https://open.spotify.com/artist/6eUKZXaKkcviH0Ku9w2n3V"
          },
          "href": "https://api.spotify.com/v1/artists/6eUKZXaKkcviH0Ku9w2n3V",
          "id": "6eUKZXaKkcviH0Ku9w2n3V",
          "name": "Ed Sheeran",
          "type": "artist",
          "uri": "spotify:artist:6eUKZXaKkcviH0Ku9w2n3V"
        }
      ],
      "available_markets": [
        "AR",
        "AU",
        "AT",
        "BE",
        "BO",
        "BR",
        "BG",
        "CA",
        "CL",
        "CO",
        "CR",
        "CY",
        "CZ",
        "DK",
        "DO",
        "DE",
        "EC",
        "EE",
        "SV",
        "FI",
        "FR",
        "GR",
        "GT",
        "HN",
        "HK",
        "HU",
        "IS",
        "IE",
        "IT",
        "LV",
        "LT",
        "LU",
        "MY",
        "MT",
        "MX",
        "NL",
        "NZ",
        "NI",
        "NO",
        "PA",
        "PY",
        "PE",
        "PH",
        "PL",
        "PT",
        "SG",
        "SK",
        "ES",
        "SE",
        "CH",
        "TW",
        "TR",
        "UY",
        "US",
        "GB",
        "AD",
        "LI",
        "MC",
        "ID",
        "JP",
        "TH",
        "VN",
        "RO",
        "IL",
        "ZA",
        "SA",
        "AE",
        "BH",
        "QA",
        "OM",
        "KW",
        "EG",
        "MA",
        "DZ",
        "TN",
        "LB",
        "JO",
        "PS",
        "IN",
        "KZ",
        "MD",
        "UA",
        "AL",
        "BA",
        "HR",
        "ME",
        "MK",
        "RS",
        "SI",
        "KR",
        "BD",
        "PK",
        "LK",
        "GH",
        "KE",
        "NG",
        "TZ",
        "UG",
        "AG",
        "AM",
        "BS",
        "BB",
        "BZ",
        "BT",
        "BW",
        "BF",
        "CV",
        "CW",
        "DM",
        "FJ",
        "GM",
        "GE",
        "GD",
        "GW",
        "GY",
        "HT",
        "JM",
        "KI",
        "LS",
        "LR",
        "MW",
        "MV",
        "ML",
        "MH",
        "FM",
        "NA",
        "NR",
        "NE",
        "PW",
        "PG",
        "PR",
        "WS",
        "SM",
        "ST",
        "SN",
        "SC",
        "SL",
        "SB",
        "KN",
        "LC",
        "VC",
        "SR",
        "TL",
        "TO",
        "TT",
        "TV",
        "VU",
        "AZ",
        "BN",
        "BI",
        "KH",
        "CM",
        "TD",
        "KM",
        "GQ",
        "SZ",
        "GA",
        "GN",
        "KG",
        "LA",
        "MO",
        "MR",
        "MN",
        "NP",
        "RW",
        "TG",
        "UZ",
        "ZW",
        "BJ",
        "MG",
        "MU",
        "MZ",
        "AO",
        "CI",
        "DJ",
        "ZM",
        "CD",
        "CG",
        "IQ",
        "LY",
        "TJ",
        "VE",
        "ET",
        "XK"
      ],
      "disc_number": 1,
      "duration_ms": 206008,
      "explicit": false,
      "external_urls": {
        "spotify": "https://open.spotify.com/track/6sOgmZZirRoPic91xQ0pl6"
      },
      "href": "https://api.spotify.com/v1/tracks/6sOgmZZirRoPic91xQ0pl6",
      "id": "6sOgmZZirRoPic91xQ0pl6",
      "name": "Punchline",
      "preview_url": null,
      "track_number": 11,
      "type": "track",
      "uri": "spotify:track:6sOgmZZirRoPic91xQ0pl6",
      "is_local": false
    },
    {
      "artists": [
        {
          "external_urls": {
            "spotify": "https://open.spotify.com/artist/6eUKZXaKkcviH0Ku9w2n3V"
          },
          "href": "https://api.spotify.com/v1/artists/6eUKZXaKkcviH0Ku9w2n3V",
          "id": "6eUKZXaKkcviH0Ku9w2n3V",
          "name": "Ed Sheeran",
          "type": "artist",
          "uri": "spotify:artist:6eUKZXaKkcviH0Ku9w2n3V"
        }
      ],
      "available_markets": [
        "AR",
        "AU",
        "AT",
        "BE",
        "BO",
        "BR",
        "BG",
        "CA",
        "CL",
        "CO",
        "CR",
        "CY",
        "CZ",
        "DK",
        "DO",
        "DE",
        "EC",
        "EE",
        "SV",
        "FI",
        "FR",
        "GR",
        "GT",
        "HN",
        "HK",
        "HU",
        "IS",
        "IE",
        "IT",
        "LV",
        "LT",
        "LU",
        "MY",
        "MT",
        "MX",
        "NL",
        "NZ",
        "NI",
        "NO",
        "PA",
        "PY",
        "PE",
        "PH",
        "PL",
        "PT",
        "SG",
        "SK",
        "ES",
        "SE",
        "CH",
        "TW",
        "TR",
        "UY",
        "US",
        "GB",
        "AD",
        "LI",
        "MC",
        "ID",
        "JP",
        "TH",
        "VN",
        "RO",
        "IL",
        "ZA",
        "SA",
        "AE",
        "BH",
        "QA",
        "OM",
        "KW",
        "EG",
        "MA",
        "DZ",
        "TN",
        "LB",
        "JO",
        "PS",
        "IN",
        "KZ",
        "MD",
        "UA",
        "AL",
        "BA",
        "HR",
        "ME",
        "MK",
        "RS",
        "SI",
        "KR",
        "BD",
        "PK",
        "LK",
        "GH",
        "KE",
        "NG",
        "TZ",
        "UG",
        "AG",
        "AM",
        "BS",
        "BB",
        "BZ",
        "BT",
        "BW",
        "BF",
        "CV",
        "CW",
        "DM",
        "FJ",
        "GM",
        "GE",
        "GD",
        "GW",
        "GY",
        "HT",
        "JM",
        "KI",
        "LS",
        "LR",
        "MW",
        "MV",
        "ML",
        "MH",
        "FM",
        "NA",
        "NR",
        "NE",
        "PW",
        "PG",
        "PR",
        "WS",
        "SM",
        "ST",
        "SN",
        "SC",
        "SL",
        "SB",
        "KN",
        "LC",
        "VC",
        "SR",
        "TL",
        "TO",
        "TT",
        "TV",
        "VU",
        "AZ",
        "BN",
        "BI",
        "KH",
        "CM",
        "TD",
        "KM",
        "GQ",
        "SZ",
        "GA",
        "GN",
        "KG",
        "LA",
        "MO",
        "MR",
        "MN",
        "NP",
        "RW",
        "TG",
        "UZ",
        "ZW",
        "BJ",
        "MG",
        "MU",
        "MZ",
        "AO",
        "CI",
        "DJ",
        "ZM",
        "CD",
        "CG",
        "IQ",
        "LY",
        "TJ",
        "VE",
        "ET",
        "XK"
      ],
      "disc_number": 1,
      "duration_ms": 175878,
      "explicit": false,
      "external_urls": {
        "spotify": "https://open.spotify.com/track/6VV2HwNlosZHFPYyPezX4Q"
      },
      "href": "https://api.spotify.com/v1/tracks/6VV2HwNlosZHFPYyPezX4Q",
      "id": "6VV2HwNlosZHFPYyPezX4Q",
      "name": "When Will I Be Alright",
      "preview_url": null,
      "track_number": 12,
      "type": "track",
      "uri": "spotify:track:6VV2HwNlosZHFPYyPezX4Q",
      "is_local": false
    },
    {
      "artists": [
        {
          "external_urls": {
            "spotify": "https://open.spotify.com/artist/6eUKZXaKkcviH0Ku9w2n3V"
          },
          "href": "https://api.spotify.com/v1/artists/6eUKZXaKkcviH0Ku9w2n3V",
          "id": "6eUKZXaKkcviH0Ku9w2n3V",
          "name": "Ed Sheeran",
          "type": "artist",
          "uri": "spotify:artist:6eUKZXaKkcviH0Ku9w2n3V"
        }
      ],
      "available_markets": [
        "AR",
        "AU",
        "AT",
        "BE",
        "BO",
        "BR",
        "BG",
        "CA",
        "CL",
        "CO",
        "CR",
        "CY",
        "CZ",
        "DK",
        "DO",
        "DE",
        "EC",
        "EE",
        "SV",
        "FI",
        "FR",
        "GR",
        "GT",
        "HN",
        "HK",
        "HU",
        "IS",
        "IE",
        "IT",
        "LV",
        "LT",
        "LU",
        "MY",
        "MT",
        "MX",
        "NL",
        "NZ",
        "NI",
        "NO",
        "PA",
        "PY",
        "PE",
        "PH",
        "PL",
        "PT",
        "SG",
        "SK",
        "ES",
        "SE",
        "CH",
        "TW",
        "TR",
        "UY",
        "US",
        "GB",
        "AD",
        "LI",
        "MC",
        "ID",
        "JP",
        "TH",
        "VN",
        "RO",
        "IL",
        "ZA",
        "SA",
        "AE",
        "BH",
        "QA",
        "OM",
        "KW",
        "EG",
        "MA",
        "DZ",
        "TN",
        "LB",
        "JO",
        "PS",
        "IN",
        "KZ",
        "MD",
        "UA",
        "AL",
        "BA",
        "HR",
        "ME",
        "MK",
        "RS",
        "SI",
        "KR",
        "BD",
        "PK",
        "LK",
        "GH",
        "KE",
        "NG",
        "TZ",
        "UG",
        "AG",
        "AM",
        "BS",
        "BB",
        "BZ",
        "BT",
        "BW",
        "BF",
        "CV",
        "CW",
        "DM",
        "FJ",
        "GM",
        "GE",
        "GD",
        "GW",
        "GY",
        "HT",
        "JM",
        "KI",
        "LS",
        "LR",
        "MW",
        "MV",
        "ML",
        "MH",
        "FM",
        "NA",
        "NR",
        "NE",
        "PW",
        "PG",
        "PR",
        "WS",
        "SM",
        "ST",
        "SN",
        "SC",
        "SL",
        "SB",
        "KN",
        "LC",
        "VC",
        "SR",
        "TL",
        "TO",
        "TT",
        "TV",
        "VU",
        "AZ",
        "BN",
        "BI",
        "KH",
        "CM",
        "TD",
        "KM",
        "GQ",
        "SZ",
        "GA",
        "GN",
        "KG",
        "LA",
        "MO",
        "MR",
        "MN",
        "NP",
        "RW",
        "TG",
        "UZ",
        "ZW",
        "BJ",
        "MG",
        "MU",
        "MZ",
        "AO",
        "CI",
        "DJ",
        "ZM",
        "CD",
        "CG",
        "IQ",
        "LY",
        "TJ",
        "VE",
        "ET",
        "XK"
      ],
      "disc_number": 1,
      "duration_ms": 252318,
      "explicit": true,
      "external_urls": {
        "spotify": "https://open.spotify.com/track/45a6lZchOMRp90XN1gC4II"
      },
      "href": "https://api.spotify.com/v1/tracks/45a6lZchOMRp90XN1gC4II",
      "id": "45a6lZchOMRp90XN1gC4II",
      "name": "The Day I Was Born",
      "preview_url": null,
      "track_number": 13,
      "type": "track",
      "uri": "spotify:track:45a6lZchOMRp90XN1gC4II",
      "is_local": false
    },
    {
      "artists": [
        {
          "external_urls": {
            "spotify": "https://open.spotify.com/artist/6eUKZXaKkcviH0Ku9w2n3V"
          },
          "href": "https://api.spotify.com/v1/artists/6eUKZXaKkcviH0Ku9w2n3V",
          "id": "6eUKZXaKkcviH0Ku9w2n3V",
          "name": "Ed Sheeran",
          "type": "artist",
          "uri": "spotify:artist:6eUKZXaKkcviH0Ku9w2n3V"
        }
      ],
      "available_markets": [
        "AR",
        "AU",
        "AT",
        "BE",
        "BO",
        "BR",
        "BG",
        "CA",
        "CL",
        "CO",
        "CR",
        "CY",
        "CZ",
        "DK",
        "DO",
        "DE",
        "EC",
        "EE",
        "SV",
        "FI",
        "FR",
        "GR",
        "GT",
        "HN",
        "HK",
        "HU",
        "IS",
        "IE",
        "IT",
        "LV",
        "LT",
        "LU",
        "MY",
        "MT",
        "MX",
        "NL",
        "NZ",
        "NI",
        "NO",
        "PA",
        "PY",
        "PE",
        "PH",
        "PL",
        "PT",
        "SG",
        "SK",
        "ES",
        "SE",
        "CH",
        "TW",
        "TR",
        "UY",
        "US",
        "GB",
        "AD",
        "LI",
        "MC",
        "ID",
        "JP",
        "TH",
        "VN",
        "RO",
        "IL",
        "ZA",
        "SA",
        "AE",
        "BH",
        "QA",
        "OM",
        "KW",
        "EG",
        "MA",
        "DZ",
        "TN",
        "LB",
        "JO",
        "PS",
        "IN",
        "KZ",
        "MD",
        "UA",
        "AL",
        "BA",
        "HR",
        "ME",
        "MK",
        "RS",
        "SI",
        "KR",
        "BD",
        "PK",
        "LK",
        "GH",
        "KE",
        "NG",
        "TZ",
        "UG",
        "AG",
        "AM",
        "BS",
        "BB",
        "BZ",
        "BT",
        "BW",
        "BF",
        "CV",
        "CW",
        "DM",
        "FJ",
        "GM",
        "GE",
        "GD",
        "GW",
        "GY",
        "HT",
        "JM",
        "KI",
        "LS",
        "LR",
        "MW",
        "MV",
        "ML",
        "MH",
        "FM",
        "NA",
        "NR",
        "NE",
        "PW",
        "PG",
        "PR",
        "WS",
        "SM",
        "ST",
        "SN",
        "SC",
        "SL",
        "SB",
        "KN",
        "LC",
        "VC",
        "SR",
        "TL",
        "TO",
        "TT",
        "TV",
        "VU",
        "AZ",
        "BN",
        "BI",
        "KH",
        "CM",
        "TD",
        "KM",
        "GQ",
        "SZ",
        "GA",
        "GN",
        "KG",
        "LA",
        "MO",
        "MR",
        "MN",
        "NP",
        "RW",
        "TG",
        "UZ",
        "ZW",
        "BJ",
        "MG",
        "MU",
        "MZ",
        "AO",
        "CI",
        "DJ",
        "ZM",
        "CD",
        "CG",
        "IQ",
        "LY",
        "TJ",
        "VE",
        "ET",
        "XK"
      ],
      "disc_number": 1,
      "duration_ms": 253881,
      "explicit": false,
      "external_urls": {
        "spotify": "https://open.spotify.com/track/3V0WFHUDCYSCQkhnK9Yzn5"
      },
      "href": "https://api.spotify.com/v1/tracks/3V0WFHUDCYSCQkhnK9Yzn5",
      "id": "3V0WFHUDCYSCQkhnK9Yzn5",
      "name": "Head > Heels",
      "preview_url": null,
      "track_number": 14,
      "type": "track",
      "uri": "spotify:track:3V0WFHUDCYSCQkhnK9Yzn5",
      "is_local": false
    },
    {
      "artists": [
        {
          "external_urls": {
            "spotify": "https://open.spotify.com/artist/6eUKZXaKkcviH0Ku9w2n3V"
          },
          "href": "https://api.spotify.com/v1/artists/6eUKZXaKkcviH0Ku9w2n3V",
          "id": "6eUKZXaKkcviH0Ku9w2n3V",
          "name": "Ed Sheeran",
          "type": "artist",
          "uri": "spotify:artist:6eUKZXaKkcviH0Ku9w2n3V"
        }
      ],
      "available_markets": [
        "AR",
        "AU",
        "AT",
        "BE",
        "BO",
        "BR",
        "BG",
        "CA",
        "CL",
        "CO",
        "CR",
        "CY",
        "CZ",
        "DK",
        "DO",
        "DE",
        "EC",
        "EE",
        "SV",
        "FI",
        "FR",
        "GR",
        "GT",
        "HN",
        "HK",
        "HU",
        "IS",
        "IE",
        "IT",
        "LV",
        "LT",
        "LU",
        "MY",
        "MT",
        "MX",
        "NL",
        "NZ",
        "NI",
        "NO",
        "PA",
        "PY",
        "PE",
        "PH",
        "PL",
        "PT",
        "SG",
        "SK",
        "ES",
        "SE",
        "CH",
        "TW",
        "TR",
        "UY",
        "US",
        "GB",
        "AD",
        "LI",
        "MC",
        "ID",
        "JP",
        "TH",
        "VN",
        "RO",
        "IL",
        "ZA",
        "SA",
        "AE",
        "BH",
        "QA",
        "OM",
        "KW",
        "EG",
        "MA",
        "DZ",
        "TN",
        "LB",
        "JO",
        "PS",
        "IN",
        "KZ",
        "MD",
        "UA",
        "AL",
        "BA",
        "HR",
        "ME",
        "MK",
        "RS",
        "SI",
        "KR",
        "BD",
        "PK",
        "LK",
        "GH",
        "KE",
        "NG",
        "TZ",
        "UG",
        "AG",
        "AM",
        "BS",
        "BB",
        "BZ",
        "BT",
        "BW",
        "BF",
        "CV",
        "CW",
        "DM",
        "FJ",
        "GM",
        "GE",
        "GD",
        "GW",
        "GY",
        "HT",
        "JM",
        "KI",
        "LS",
        "LR",
        "MW",
        "MV",
        "ML",
        "MH",
        "FM",
        "NA",
        "NR",
        "NE",
        "PW",
        "PG",
        "PR",
        "WS",
        "SM",
        "ST",
        "SN",
        "SC",
        "SL",
        "SB",
        "KN",
        "LC",
        "VC",
        "SR",
        "TL",
        "TO",
        "TT",
        "TV",
        "VU",
        "AZ",
        "BN",
        "BI",
        "KH",
        "CM",
        "TD",
        "KM",
        "GQ",
        "SZ",
        "GA",
        "GN",
        "KG",
        "LA",
        "MO",
        "MR",
        "MN",
        "NP",
        "RW",
        "TG",
        "UZ",
        "ZW",
        "BJ",
        "MG",
        "MU",
        "MZ",
        "AO",
        "CI",
        "DJ",
        "ZM",
        "CD",
        "CG",
        "IQ",
        "LY",
        "TJ",
        "VE",
        "ET",
        "XK"
      ],
      "disc_number": 2,
      "duration_ms": 174343,
      "explicit": false,
      "external_urls": {
        "spotify": "https://open.spotify.com/track/26eyElBDPNcCotyeb8GER6"
      },
      "href": "https://api.spotify.com/v1/tracks/26eyElBDPNcCotyeb8GER6",
      "id": "26eyElBDPNcCotyeb8GER6",
      "name": "Magical - Live from Brantlie’s Living Room",
      "preview_url": null,
      "track_number": 1,
      "type": "track",
      "uri": "spotify:track:26eyElBDPNcCotyeb8GER6",
      "is_local": false
    },
    {
      "artists": [
        {
          "external_urls": {
            "spotify": "https://open.spotify.com/artist/6eUKZXaKkcviH0Ku9w2n3V"
          },
          "href": "https://api.spotify.com/v1/artists/6eUKZXaKkcviH0Ku9w2n3V",
          "id": "6eUKZXaKkcviH0Ku9w2n3V",
          "name": "Ed Sheeran",
          "type": "artist",
          "uri": "spotify:artist:6eUKZXaKkcviH0Ku9w2n3V"
        }
      ],
      "available_markets": [
        "AR",
        "AU",
        "AT",
        "BE",
        "BO",
        "BR",
        "BG",
        "CA",
        "CL",
        "CO",
        "CR",
        "CY",
        "CZ",
        "DK",
        "DO",
        "DE",
        "EC",
        "EE",
        "SV",
        "FI",
        "FR",
        "GR",
        "GT",
        "HN",
        "HK",
        "HU",
        "IS",
        "IE",
        "IT",
        "LV",
        "LT",
        "LU",
        "MY",
        "MT",
        "MX",
        "NL",
        "NZ",
        "NI",
        "NO",
        "PA",
        "PY",
        "PE",
        "PH",
        "PL",
        "PT",
        "SG",
        "SK",
        "ES",
        "SE",
        "CH",
        "TW",
        "TR",
        "UY",
        "US",
        "GB",
        "AD",
        "LI",
        "MC",
        "ID",
        "JP",
        "TH",
        "VN",
        "RO",
        "IL",
        "ZA",
        "SA",
        "AE",
        "BH",
        "QA",
        "OM",
        "KW",
        "EG",
        "MA",
        "DZ",
        "TN",
        "LB",
        "JO",
        "PS",
        "IN",
        "KZ",
        "MD",
        "UA",
        "AL",
        "BA",
        "HR",
        "ME",
        "MK",
        "RS",
        "SI",
        "KR",
        "BD",
        "PK",
        "LK",
        "GH",
        "KE",
        "NG",
        "TZ",
        "UG",
        "AG",
        "AM",
        "BS",
        "BB",
        "BZ",
        "BT",
        "BW",
        "BF",
        "CV",
        "CW",
        "DM",
        "FJ",
        "GM",
        "GE",
        "GD",
        "GW",
        "GY",
        "HT",
        "JM",
        "KI",
        "LS",
        "LR",
        "MW",
        "MV",
        "ML",
        "MH",
        "FM",
        "NA",
        "NR",
        "NE",
        "PW",
        "PG",
        "PR",
        "WS",
        "SM",
        "ST",
        "SN",
        "SC",
        "SL",
        "SB",
        "KN",
        "LC",
        "VC",
        "SR",
        "TL",
        "TO",
        "TT",
        "TV",
        "VU",
        "AZ",
        "BN",
        "BI",
        "KH",
        "CM",
        "TD",
        "KM",
        "GQ",
        "SZ",
        "GA",
        "GN",
        "KG",
        "LA",
        "MO",
        "MR",
        "MN",
        "NP",
        "RW",
        "TG",
        "UZ",
        "ZW",
        "BJ",
        "MG",
        "MU",
        "MZ",
        "AO",
        "CI",
        "DJ",
        "ZM",
        "CD",
        "CG",
        "IQ",
        "LY",
        "TJ",
        "VE",
        "ET",
        "XK"
      ],
      "disc_number": 2,
      "duration_ms": 201568,
      "explicit": false,
      "external_urls": {
        "spotify": "https://open.spotify.com/track/26vVj2jF7opp0pTFTSNtZS"
      },
      "href": "https://api.spotify.com/v1/tracks/26vVj2jF7opp0pTFTSNtZS",
      "id": "26vVj2jF7opp0pTFTSNtZS",
      "name": "England - Live from Maynard’s Living Room",
      "preview_url": null,
      "track_number": 2,
      "type": "track",
      "uri": "spotify:track:26vVj2jF7opp0pTFTSNtZS",
      "is_local": false
    },
    {
      "artists": [
        {
          "external_urls": {
            "spotify": "https://open.spotify.com/artist/6eUKZXaKkcviH0Ku9w2n3V"
          },
          "href": "https://api.spotify.com/v1/artists/6eUKZXaKkcviH0Ku9w2n3V",
          "id": "6eUKZXaKkcviH0Ku9w2n3V",
          "name": "Ed Sheeran",
          "type": "artist",
          "uri": "spotify:artist:6eUKZXaKkcviH0Ku9w2n3V"
        }
      ],
      "available_markets": [
        "AR",
        "AU",
        "AT",
        "BE",
        "BO",
        "BR",
        "BG",
        "CA",
        "CL",
        "CO",
        "CR",
        "CY",
        "CZ",
        "DK",
        "DO",
        "DE",
        "EC",
        "EE",
        "SV",
        "FI",
        "FR",
        "GR",
        "GT",
        "HN",
        "HK",
        "HU",
        "IS",
        "IE",
        "IT",
        "LV",
        "LT",
        "LU",
        "MY",
        "MT",
        "MX",
        "NL",
        "NZ",
        "NI",
        "NO",
        "PA",
        "PY",
        "PE",
        "PH",
        "PL",
        "PT",
        "SG",
        "SK",
        "ES",
        "SE",
        "CH",
        "TW",
        "TR",
        "UY",
        "US",
        "GB",
        "AD",
        "LI",
        "MC",
        "ID",
        "JP",
        "TH",
        "VN",
        "RO",
        "IL",
        "ZA",
        "SA",
        "AE",
        "BH",
        "QA",
        "OM",
        "KW",
        "EG",
        "MA",
        "DZ",
        "TN",
        "LB",
        "JO",
        "PS",
        "IN",
        "KZ",
        "MD",
        "UA",
        "AL",
        "BA",
        "HR",
        "ME",
        "MK",
        "RS",
        "SI",
        "KR",
        "BD",
        "PK",
        "LK",
        "GH",
        "KE",
        "NG",
        "TZ",
        "UG",
        "AG",
        "AM",
        "BS",
        "BB",
        "BZ",
        "BT",
        "BW",
        "BF",
        "CV",
        "CW",
        "DM",
        "FJ",
        "GM",
        "GE",
        "GD",
        "GW",
        "GY",
        "HT",
        "JM",
        "KI",
        "LS",
        "LR",
        "MW",
        "MV",
        "ML",
        "MH",
        "FM",
        "NA",
        "NR",
        "NE",
        "PW",
        "PG",
        "PR",
        "WS",
        "SM",
        "ST",
        "SN",
        "SC",
        "SL",
        "SB",
        "KN",
        "LC",
        "VC",
        "SR",
        "TL",
        "TO",
        "TT",
        "TV",
        "VU",
        "AZ",
        "BN",
        "BI",
        "KH",
        "CM",
        "TD",
        "KM",
        "GQ",
        "SZ",
        "GA",
        "GN",
        "KG",
        "LA",
        "MO",
        "MR",
        "MN",
        "NP",
        "RW",
        "TG",
        "UZ",
        "ZW",
        "BJ",
        "MG",
        "MU",
        "MZ",
        "AO",
        "CI",
        "DJ",
        "ZM",
        "CD",
        "CG",
        "IQ",
        "LY",
        "TJ",
        "VE",
        "ET",
        "XK"
      ],
      "disc_number": 2,
      "duration_ms": 174165,
      "explicit": false,
      "external_urls": {
        "spotify": "https://open.spotify.com/track/4hjpUPLh1WJ1tBNjFsgppU"
      },
      "href": "https://api.spotify.com/v1/tracks/4hjpUPLh1WJ1tBNjFsgppU",
      "id": "4hjpUPLh1WJ1tBNjFsgppU",
      "name": "Amazing - Live from Kia’s Living Room",
      "preview_url": null,
      "track_number": 3,
      "type": "track",
      "uri": "spotify:track:4hjpUPLh1WJ1tBNjFsgppU",
      "is_local": false
    },
    {
      "artists": [
        {
          "external_urls": {
            "spotify": "https://open.spotify.com/artist/6eUKZXaKkcviH0Ku9w2n3V"
          },
          "href": "https://api.spotify.com/v1/artists/6eUKZXaKkcviH0Ku9w2n3V",
          "id": "6eUKZXaKkcviH0Ku9w2n3V",
          "name": "Ed Sheeran",
          "type": "artist",
          "uri": "spotify:artist:6eUKZXaKkcviH0Ku9w2n3V"
        }
      ],
      "available_markets": [
        "AR",
        "AU",
        "AT",
        "BE",
        "BO",
        "BR",
        "BG",
        "CA",
        "CL",
        "CO",
        "CR",
        "CY",
        "CZ",
        "DK",
        "DO",
        "DE",
        "EC",
        "EE",
        "SV",
        "FI",
        "FR",
        "GR",
        "GT",
        "HN",
        "HK",
        "HU",
        "IS",
        "IE",
        "IT",
        "LV",
        "LT",
        "LU",
        "MY",
        "MT",
        "MX",
        "NL",
        "NZ",
        "NI",
        "NO",
        "PA",
        "PY",
        "PE",
        "PH",
        "PL",
        "PT",
        "SG",
        "SK",
        "ES",
        "SE",
        "CH",
        "TW",
        "TR",
        "UY",
        "US",
        "GB",
        "AD",
        "LI",
        "MC",
        "ID",
        "JP",
        "TH",
        "VN",
        "RO",
        "IL",
        "ZA",
        "SA",
        "AE",
        "BH",
        "QA",
        "OM",
        "KW",
        "EG",
        "MA",
        "DZ",
        "TN",
        "LB",
        "JO",
        "PS",
        "IN",
        "KZ",
        "MD",
        "UA",
        "AL",
        "BA",
        "HR",
        "ME",
        "MK",
        "RS",
        "SI",
        "KR",
        "BD",
        "PK",
        "LK",
        "GH",
        "KE",
        "NG",
        "TZ",
        "UG",
        "AG",
        "AM",
        "BS",
        "BB",
        "BZ",
        "BT",
        "BW",
        "BF",
        "CV",
        "CW",
        "DM",
        "FJ",
        "GM",
        "GE",
        "GD",
        "GW",
        "GY",
        "HT",
        "JM",
        "KI",
        "LS",
        "LR",
        "MW",
        "MV",
        "ML",
        "MH",
        "FM",
        "NA",
        "NR",
        "NE",
        "PW",
        "PG",
        "PR",
        "WS",
        "SM",
        "ST",
        "SN",
        "SC",
        "SL",
        "SB",
        "KN",
        "LC",
        "VC",
        "SR",
        "TL",
        "TO",
        "TT",
        "TV",
        "VU",
        "AZ",
        "BN",
        "BI",
        "KH",
        "CM",
        "TD",
        "KM",
        "GQ",
        "SZ",
        "GA",
        "GN",
        "KG",
        "LA",
        "MO",
        "MR",
        "MN",
        "NP",
        "RW",
        "TG",
        "UZ",
        "ZW",
        "BJ",
        "MG",
        "MU",
        "MZ",
        "AO",
        "CI",
        "DJ",
        "ZM",
        "CD",
        "CG",
        "IQ",
        "LY",
        "TJ",
        "VE",
        "ET",
        "XK"
      ],
      "disc_number": 2,
      "duration_ms": 218887,
      "explicit": true,
      "external_urls": {
        "spotify": "https://open.spotify.com/track/4uLja2eQJ8mBoA4QmVy4Jb"
      },
      "href": "https://api.spotify.com/v1/tracks/4uLja2eQJ8mBoA4QmVy4Jb",
      "id": "4uLja2eQJ8mBoA4QmVy4Jb",
      "name": "Plastic Bag - Live from Alex’s Living Room",
      "preview_url": null,
      "track_number": 4,
      "type": "track",
      "uri": "spotify:track:4uLja2eQJ8mBoA4QmVy4Jb",
      "is_local": false
    },
    {
      "artists": [
        {
          "external_urls": {
            "spotify": "https://open.spotify.com/artist/6eUKZXaKkcviH0Ku9w2n3V"
          },
          "href": "https://api.spotify.com/v1/artists/6eUKZXaKkcviH0Ku9w2n3V",
          "id": "6eUKZXaKkcviH0Ku9w2n3V",
          "name": "Ed Sheeran",
          "type": "artist",
          "uri": "spotify:artist:6eUKZXaKkcviH0Ku9w2n3V"
        }
      ],
      "available_markets": [
        "AR",
        "AU",
        "AT",
        "BE",
        "BO",
        "BR",
        "BG",
        "CA",
        "CL",
        "CO",
        "CR",
        "CY",
        "CZ",
        "DK",
        "DO",
        "DE",
        "EC",
        "EE",
        "SV",
        "FI",
        "FR",
        "GR",
        "GT",
        "HN",
        "HK",
        "HU",
        "IS",
        "IE",
        "IT",
        "LV",
        "LT",
        "LU",
        "MY",
        "MT",
        "MX",
        "NL",
        "NZ",
        "NI",
        "NO",
        "PA",
        "PY",
        "PE",
        "PH",
        "PL",
        "PT",
        "SG",
        "SK",
        "ES",
        "SE",
        "CH",
        "TW",
        "TR",
        "UY",
        "US",
        "GB",
        "AD",
        "LI",
        "MC",
        "ID",
        "JP",
        "TH",
        "VN",
        "RO",
        "IL",
        "ZA",
        "SA",
        "AE",
        "BH",
        "QA",
        "OM",
        "KW",
        "EG",
        "MA",
        "DZ",
        "TN",
        "LB",
        "JO",
        "PS",
        "IN",
        "KZ",
        "MD",
        "UA",
        "AL",
        "BA",
        "HR",
        "ME",
        "MK",
        "RS",
        "SI",
        "KR",
        "BD",
        "PK",
        "LK",
        "GH",
        "KE",
        "NG",
        "TZ",
        "UG",
        "AG",
        "AM",
        "BS",
        "BB",
        "BZ",
        "BT",
        "BW",
        "BF",
        "CV",
        "CW",
        "DM",
        "FJ",
        "GM",
        "GE",
        "GD",
        "GW",
        "GY",
        "HT",
        "JM",
        "KI",
        "LS",
        "LR",
        "MW",
        "MV",
        "ML",
        "MH",
        "FM",
        "NA",
        "NR",
        "NE",
        "PW",
        "PG",
        "PR",
        "WS",
        "SM",
        "ST",
        "SN",
        "SC",
        "SL",
        "SB",
        "KN",
        "LC",
        "VC",
        "SR",
        "TL",
        "TO",
        "TT",
        "TV",
        "VU",
        "AZ",
        "BN",
        "BI",
        "KH",
        "CM",
        "TD",
        "KM",
        "GQ",
        "SZ",
        "GA",
        "GN",
        "KG",
        "LA",
        "MO",
        "MR",
        "MN",
        "NP",
        "RW",
        "TG",
        "UZ",
        "ZW",
        "BJ",
        "MG",
        "MU",
        "MZ",
        "AO",
        "CI",
        "DJ",
        "ZM",
        "CD",
        "CG",
        "IQ",
        "LY",
        "TJ",
        "VE",
        "ET",
        "XK"
      ],
      "disc_number": 2,
      "duration_ms": 141203,
      "explicit": false,
      "external_urls": {
        "spotify": "https://open.spotify.com/track/5SBrQlvC8l1tW5wNSi0Rlu"
      },
      "href": "https://api.spotify.com/v1/tracks/5SBrQlvC8l1tW5wNSi0Rlu",
      "id": "5SBrQlvC8l1tW5wNSi0Rlu",
      "name": "Blue - Live from Sarom’s Living Room",
      "preview_url": null,
      "track_number": 5,
      "type": "track",
      "uri": "spotify:track:5SBrQlvC8l1tW5wNSi0Rlu",
      "is_local": false
    },
    {
      "artists": [
        {
          "external_urls": {
            "spotify": "https://open.spotify.com/artist/6eUKZXaKkcviH0Ku9w2n3V"
          },
          "href": "https://api.spotify.com/v1/artists/6eUKZXaKkcviH0Ku9w2n3V",
          "id": "6eUKZXaKkcviH0Ku9w2n3V",
          "name": "Ed Sheeran",
          "type": "artist",
          "uri": "spotify:artist:6eUKZXaKkcviH0Ku9w2n3V"
        }
      ],
      "available_markets": [
        "AR",
        "AU",
        "AT",
        "BE",
        "BO",
        "BR",
        "BG",
        "CA",
        "CL",
        "CO",
        "CR",
        "CY",
        "CZ",
        "DK",
        "DO",
        "DE",
        "EC",
        "EE",
        "SV",
        "FI",
        "FR",
        "GR",
        "GT",
        "HN",
        "HK",
        "HU",
        "IS",
        "IE",
        "IT",
        "LV",
        "LT",
        "LU",
        "MY",
        "MT",
        "MX",
        "NL",
        "NZ",
        "NI",
        "NO",
        "PA",
        "PY",
        "PE",
        "PH",
        "PL",
        "PT",
        "SG",
        "SK",
        "ES",
        "SE",
        "CH",
        "TW",
        "TR",
        "UY",
        "US",
        "GB",
        "AD",
        "LI",
        "MC",
        "ID",
        "JP",
        "TH",
        "VN",
        "RO",
        "IL",
        "ZA",
        "SA",
        "AE",
        "BH",
        "QA",
        "OM",
        "KW",
        "EG",
        "MA",
        "DZ",
        "TN",
        "LB",
        "JO",
        "PS",
        "IN",
        "KZ",
        "MD",
        "UA",
        "AL",
        "BA",
        "HR",
        "ME",
        "MK",
        "RS",
        "SI",
        "KR",
        "BD",
        "PK",
        "LK",
        "GH",
        "KE",
        "NG",
        "TZ",
        "UG",
        "AG",
        "AM",
        "BS",
        "BB",
        "BZ",
        "BT",
        "BW",
        "BF",
        "CV",
        "CW",
        "DM",
        "FJ",
        "GM",
        "GE",
        "GD",
        "GW",
        "GY",
        "HT",
        "JM",
        "KI",
        "LS",
        "LR",
        "MW",
        "MV",
        "ML",
        "MH",
        "FM",
        "NA",
        "NR",
        "NE",
        "PW",
        "PG",
        "PR",
        "WS",
        "SM",
        "ST",
        "SN",
        "SC",
        "SL",
        "SB",
        "KN",
        "LC",
        "VC",
        "SR",
        "TL",
        "TO",
        "TT",
        "TV",
        "VU",
        "AZ",
        "BN",
        "BI",
        "KH",
        "CM",
        "TD",
        "KM",
        "GQ",
        "SZ",
        "GA",
        "GN",
        "KG",
        "LA",
        "MO",
        "MR",
        "MN",
        "NP",
        "RW",
        "TG",
        "UZ",
        "ZW",
        "BJ",
        "MG",
        "MU",
        "MZ",
        "AO",
        "CI",
        "DJ",
        "ZM",
        "CD",
        "CG",
        "IQ",
        "LY",
        "TJ",
        "VE",
        "ET",
        "XK"
      ],
      "disc_number": 2,
      "duration_ms": 195749,
      "explicit": false,
      "external_urls": {
        "spotify": "https://open.spotify.com/track/0nWELRrZYYeJaynDOVjggv"
      },
      "href": "https://api.spotify.com/v1/tracks/0nWELRrZYYeJaynDOVjggv",
      "id": "0nWELRrZYYeJaynDOVjggv",
      "name": "American Town - Live from Kari’s Living Room",
      "preview_url": null,
      "track_number": 6,
      "type": "track",
      "uri": "spotify:track:0nWELRrZYYeJaynDOVjggv",
      "is_local": false
    },
    {
      "artists": [
        {
          "external_urls": {
            "spotify": "https://open.spotify.com/artist/6eUKZXaKkcviH0Ku9w2n3V"
          },
          "href": "https://api.spotify.com/v1/artists/6eUKZXaKkcviH0Ku9w2n3V",
          "id": "6eUKZXaKkcviH0Ku9w2n3V",
          "name": "Ed Sheeran",
          "type": "artist",
          "uri": "spotify:artist:6eUKZXaKkcviH0Ku9w2n3V"
        }
      ],
      "available_markets": [
        "AR",
        "AU",
        "AT",
        "BE",
        "BO",
        "BR",
        "BG",
        "CA",
        "CL",
        "CO",
        "CR",
        "CY",
        "CZ",
        "DK",
        "DO",
        "DE",
        "EC",
        "EE",
        "SV",
        "FI",
        "FR",
        "GR",
        "GT",
        "HN",
        "HK",
        "HU",
        "IS",
        "IE",
        "IT",
        "LV",
        "LT",
        "LU",
        "MY",
        "MT",
        "MX",
        "NL",
        "NZ",
        "NI",
        "NO",
        "PA",
        "PY",
        "PE",
        "PH",
        "PL",
        "PT",
        "SG",
        "SK",
        "ES",
        "SE",
        "CH",
        "TW",
        "TR",
        "UY",
        "US",
        "GB",
        "AD",
        "LI",
        "MC",
        "ID",
        "JP",
        "TH",
        "VN",
        "RO",
        "IL",
        "ZA",
        "SA",
        "AE",
        "BH",
        "QA",
        "OM",
        "KW",
        "EG",
        "MA",
        "DZ",
        "TN",
        "LB",
        "JO",
        "PS",
        "IN",
        "KZ",
        "MD",
        "UA",
        "AL",
        "BA",
        "HR",
        "ME",
        "MK",
        "RS",
        "SI",
        "KR",
        "BD",
        "PK",
        "LK",
        "GH",
        "KE",
        "NG",
        "TZ",
        "UG",
        "AG",
        "AM",
        "BS",
        "BB",
        "BZ",
        "BT",
        "BW",
        "BF",
        "CV",
        "CW",
        "DM",
        "FJ",
        "GM",
        "GE",
        "GD",
        "GW",
        "GY",
        "HT",
        "JM",
        "KI",
        "LS",
        "LR",
        "MW",
        "MV",
        "ML",
        "MH",
        "FM",
        "NA",
        "NR",
        "NE",
        "PW",
        "PG",
        "PR",
        "WS",
        "SM",
        "ST",
        "SN",
        "SC",
        "SL",
        "SB",
        "KN",
        "LC",
        "VC",
        "SR",
        "TL",
        "TO",
        "TT",
        "TV",
        "VU",
        "AZ",
        "BN",
        "BI",
        "KH",
        "CM",
        "TD",
        "KM",
        "GQ",
        "SZ",
        "GA",
        "GN",
        "KG",
        "LA",
        "MO",
        "MR",
        "MN",
        "NP",
        "RW",
        "TG",
        "UZ",
        "ZW",
        "BJ",
        "MG",
        "MU",
        "MZ",
        "AO",
        "CI",
        "DJ",
        "ZM",
        "CD",
        "CG",
        "IQ",
        "LY",
        "TJ",
        "VE",
        "ET",
        "XK"
      ],
      "disc_number": 2,
      "duration_ms": 191808,
      "explicit": true,
      "external_urls": {
        "spotify": "https://open.spotify.com/track/2PAMpzkXfCU4NFs1IiJVhY"
      },
      "href": "https://api.spotify.com/v1/tracks/2PAMpzkXfCU4NFs1IiJVhY",
      "id": "2PAMpzkXfCU4NFs1IiJVhY",
      "name": "That’s On Me - Live from Narine’s Living Room",
      "preview_url": null,
      "track_number": 7,
      "type": "track",
      "uri": "spotify:track:2PAMpzkXfCU4NFs1IiJVhY",
      "is_local": false
    },
    {
      "artists": [
        {
          "external_urls": {
            "spotify": "https://open.spotify.com/artist/6eUKZXaKkcviH0Ku9w2n3V"
          },
          "href": "https://api.spotify.com/v1/artists/6eUKZXaKkcviH0Ku9w2n3V",
          "id": "6eUKZXaKkcviH0Ku9w2n3V",
          "name": "Ed Sheeran",
          "type": "artist",
          "uri": "spotify:artist:6eUKZXaKkcviH0Ku9w2n3V"
        }
      ],
      "available_markets": [
        "AR",
        "AU",
        "AT",
        "BE",
        "BO",
        "BR",
        "BG",
        "CA",
        "CL",
        "CO",
        "CR",
        "CY",
        "CZ",
        "DK",
        "DO",
        "DE",
        "EC",
        "EE",
        "SV",
        "FI",
        "FR",
        "GR",
        "GT",
        "HN",
        "HK",
        "HU",
        "IS",
        "IE",
        "IT",
        "LV",
        "LT",
        "LU",
        "MY",
        "MT",
        "MX",
        "NL",
        "NZ",
        "NI",
        "NO",
        "PA",
        "PY",
        "PE",
        "PH",
        "PL",
        "PT",
        "SG",
        "SK",
        "ES",
        "SE",
        "CH",
        "TW",
        "TR",
        "UY",
        "US",
        "GB",
        "AD",
        "LI",
        "MC",
        "ID",
        "JP",
        "TH",
        "VN",
        "RO",
        "IL",
        "ZA",
        "SA",
        "AE",
        "BH",
        "QA",
        "OM",
        "KW",
        "EG",
        "MA",
        "DZ",
        "TN",
        "LB",
        "JO",
        "PS",
        "IN",
        "KZ",
        "MD",
        "UA",
        "AL",
        "BA",
        "HR",
        "ME",
        "MK",
        "RS",
        "SI",
        "KR",
        "BD",
        "PK",
        "LK",
        "GH",
        "KE",
        "NG",
        "TZ",
        "UG",
        "AG",
        "AM",
        "BS",
        "BB",
        "BZ",
        "BT",
        "BW",
        "BF",
        "CV",
        "CW",
        "DM",
        "FJ",
        "GM",
        "GE",
        "GD",
        "GW",
        "GY",
        "HT",
        "JM",
        "KI",
        "LS",
        "LR",
        "MW",
        "MV",
        "ML",
        "MH",
        "FM",
        "NA",
        "NR",
        "NE",
        "PW",
        "PG",
        "PR",
        "WS",
        "SM",
        "ST",
        "SN",
        "SC",
        "SL",
        "SB",
        "KN",
        "LC",
        "VC",
        "SR",
        "TL",
        "TO",
        "TT",
        "TV",
        "VU",
        "AZ",
        "BN",
        "BI",
        "KH",
        "CM",
        "TD",
        "KM",
        "GQ",
        "SZ",
        "GA",
        "GN",
        "KG",
        "LA",
        "MO",
        "MR",
        "MN",
        "NP",
        "RW",
        "TG",
        "UZ",
        "ZW",
        "BJ",
        "MG",
        "MU",
        "MZ",
        "AO",
        "CI",
        "DJ",
        "ZM",
        "CD",
        "CG",
        "IQ",
        "LY",
        "TJ",
        "VE",
        "ET",
        "XK"
      ],
      "disc_number": 2,
      "duration_ms": 211849,
      "explicit": false,
      "external_urls": {
        "spotify": "https://open.spotify.com/track/1roO8TRLqZ0ja57mILJQlF"
      },
      "href": "https://api.spotify.com/v1/tracks/1roO8TRLqZ0ja57mILJQlF",
      "id": "1roO8TRLqZ0ja57mILJQlF",
      "name": "Page - Live from Deborah’s Living Room",
      "preview_url": null,
      "track_number": 8,
      "type": "track",
      "uri": "spotify:track:1roO8TRLqZ0ja57mILJQlF",
      "is_local": false
    },
    {
      "artists": [
        {
          "external_urls": {
            "spotify": "https://open.spotify.com/artist/6eUKZXaKkcviH0Ku9w2n3V"
          },
          "href": "https://api.spotify.com/v1/artists/6eUKZXaKkcviH0Ku9w2n3V",
          "id": "6eUKZXaKkcviH0Ku9w2n3V",
          "name": "Ed Sheeran",
          "type": "artist",
          "uri": "spotify:artist:6eUKZXaKkcviH0Ku9w2n3V"
        }
      ],
      "available_markets": [
        "AR",
        "AU",
        "AT",
        "BE",
        "BO",
        "BR",
        "BG",
        "CA",
        "CL",
        "CO",
        "CR",
        "CY",
        "CZ",
        "DK",
        "DO",
        "DE",
        "EC",
        "EE",
        "SV",
        "FI",
        "FR",
        "GR",
        "GT",
        "HN",
        "HK",
        "HU",
        "IS",
        "IE",
        "IT",
        "LV",
        "LT",
        "LU",
        "MY",
        "MT",
        "MX",
        "NL",
        "NZ",
        "NI",
        "NO",
        "PA",
        "PY",
        "PE",
        "PH",
        "PL",
        "PT",
        "SG",
        "SK",
        "ES",
        "SE",
        "CH",
        "TW",
        "TR",
        "UY",
        "US",
        "GB",
        "AD",
        "LI",
        "MC",
        "ID",
        "JP",
        "TH",
        "VN",
        "RO",
        "IL",
        "ZA",
        "SA",
        "AE",
        "BH",
        "QA",
        "OM",
        "KW",
        "EG",
        "MA",
        "DZ",
        "TN",
        "LB",
        "JO",
        "PS",
        "IN",
        "KZ",
        "MD",
        "UA",
        "AL",
        "BA",
        "HR",
        "ME",
        "MK",
        "RS",
        "SI",
        "KR",
        "BD",
        "PK",
        "LK",
        "GH",
        "KE",
        "NG",
        "TZ",
        "UG",
        "AG",
        "AM",
        "BS",
        "BB",
        "BZ",
        "BT",
        "BW",
        "BF",
        "CV",
        "CW",
        "DM",
        "FJ",
        "GM",
        "GE",
        "GD",
        "GW",
        "GY",
        "HT",
        "JM",
        "KI",
        "LS",
        "LR",
        "MW",
        "MV",
        "ML",
        "MH",
        "FM",
        "NA",
        "NR",
        "NE",
        "PW",
        "PG",
        "PR",
        "WS",
        "SM",
        "ST",
        "SN",
        "SC",
        "SL",
        "SB",
        "KN",
        "LC",
        "VC",
        "SR",
        "TL",
        "TO",
        "TT",
        "TV",
        "VU",
        "AZ",
        "BN",
        "BI",
        "KH",
        "CM",
        "TD",
        "KM",
        "GQ",
        "SZ",
        "GA",
        "GN",
        "KG",
        "LA",
        "MO",
        "MR",
        "MN",
        "NP",
        "RW",
        "TG",
        "UZ",
        "ZW",
        "BJ",
        "MG",
        "MU",
        "MZ",
        "AO",
        "CI",
        "DJ",
        "ZM",
        "CD",
        "CG",
        "IQ",
        "LY",
        "TJ",
        "VE",
        "ET",
        "XK"
      ],
      "disc_number": 2,
      "duration_ms": 151876,
      "explicit": false,
      "external_urls": {
        "spotify": "https://open.spotify.com/track/0aP608S0wKfse1LlDy9aZL"
      },
      "href": "https://api.spotify.com/v1/tracks/0aP608S0wKfse1LlDy9aZL",
      "id": "0aP608S0wKfse1LlDy9aZL",
      "name": "Midnight - Live from John’s Living Room",
      "preview_url": null,
      "track_number": 9,
      "type": "track",
      "uri": "spotify:track:0aP608S0wKfse1LlDy9aZL",
      "is_local": false
    },
    {
      "artists": [
        {
          "external_urls": {
            "spotify": "https://open.spotify.com/artist/6eUKZXaKkcviH0Ku9w2n3V"
          },
          "href": "https://api.spotify.com/v1/artists/6eUKZXaKkcviH0Ku9w2n3V",
          "id": "6eUKZXaKkcviH0Ku9w2n3V",
          "name": "Ed Sheeran",
          "type": "artist",
          "uri": "spotify:artist:6eUKZXaKkcviH0Ku9w2n3V"
        }
      ],
      "available_markets": [
        "AR",
        "AU",
        "AT",
        "BE",
        "BO",
        "BR",
        "BG",
        "CA",
        "CL",
        "CO",
        "CR",
        "CY",
        "CZ",
        "DK",
        "DO",
        "DE",
        "EC",
        "EE",
        "SV",
        "FI",
        "FR",
        "GR",
        "GT",
        "HN",
        "HK",
        "HU",
        "IS",
        "IE",
        "IT",
        "LV",
        "LT",
        "LU",
        "MY",
        "MT",
        "MX",
        "NL",
        "NZ",
        "NI",
        "NO",
        "PA",
        "PY",
        "PE",
        "PH",
        "PL",
        "PT",
        "SG",
        "SK",
        "ES",
        "SE",
        "CH",
        "TW",
        "TR",
        "UY",
        "US",
        "GB",
        "AD",
        "LI",
        "MC",
        "ID",
        "JP",
        "TH",
        "VN",
        "RO",
        "IL",
        "ZA",
        "SA",
        "AE",
        "BH",
        "QA",
        "OM",
        "KW",
        "EG",
        "MA",
        "DZ",
        "TN",
        "LB",
        "JO",
        "PS",
        "IN",
        "KZ",
        "MD",
        "UA",
        "AL",
        "BA",
        "HR",
        "ME",
        "MK",
        "RS",
        "SI",
        "KR",
        "BD",
        "PK",
        "LK",
        "GH",
        "KE",
        "NG",
        "TZ",
        "UG",
        "AG",
        "AM",
        "BS",
        "BB",
        "BZ",
        "BT",
        "BW",
        "BF",
        "CV",
        "CW",
        "DM",
        "FJ",
        "GM",
        "GE",
        "GD",
        "GW",
        "GY",
        "HT",
        "JM",
        "KI",
        "LS",
        "LR",
        "MW",
        "MV",
        "ML",
        "MH",
        "FM",
        "NA",
        "NR",
        "NE",
        "PW",
        "PG",
        "PR",
        "WS",
        "SM",
        "ST",
        "SN",
        "SC",
        "SL",
        "SB",
        "KN",
        "LC",
        "VC",
        "SR",
        "TL",
        "TO",
        "TT",
        "TV",
        "VU",
        "AZ",
        "BN",
        "BI",
        "KH",
        "CM",
        "TD",
        "KM",
        "GQ",
        "SZ",
        "GA",
        "GN",
        "KG",
        "LA",
        "MO",
        "MR",
        "MN",
        "NP",
        "RW",
        "TG",
        "UZ",
        "ZW",
        "BJ",
        "MG",
        "MU",
        "MZ",
        "AO",
        "CI",
        "DJ",
        "ZM",
        "CD",
        "CG",
        "IQ",
        "LY",
        "TJ",
        "VE",
        "ET",
        "XK"
      ],
      "disc_number": 2,
      "duration_ms": 153533,
      "explicit": false,
      "external_urls": {
        "spotify": "https://open.spotify.com/track/2Z59T7Ukc34W3adhjcskXE"
      },
      "href": "https://api.spotify.com/v1/tracks/2Z59T7Ukc34W3adhjcskXE",
      "id": "2Z59T7Ukc34W3adhjcskXE",
      "name": "Spring - Live from Emily’s Living Room",
      "preview_url": null,
      "track_number": 10,
      "type": "track",
      "uri": "spotify:track:2Z59T7Ukc34W3adhjcskXE",
      "is_local": false
    },
    {
      "artists": [
        {
          "external_urls": {
            "spotify": "https://open.spotify.com/artist/6eUKZXaKkcviH0Ku9w2n3V"
          },
          "href": "https://api.spotify.com/v1/artists/6eUKZXaKkcviH0Ku9w2n3V",
          "id": "6eUKZXaKkcviH0Ku9w2n3V",
          "name": "Ed Sheeran",
          "type": "artist",
          "uri": "spotify:artist:6eUKZXaKkcviH0Ku9w2n3V"
        }
      ],
      "available_markets": [
        "AR",
        "AU",
        "AT",
        "BE",
        "BO",
        "BR",
        "BG",
        "CA",
        "CL",
        "CO",
        "CR",
        "CY",
        "CZ",
        "DK",
        "DO",
        "DE",
        "EC",
        "EE",
        "SV",
        "FI",
        "FR",
        "GR",
        "GT",
        "HN",
        "HK",
        "HU",
        "IS",
        "IE",
        "IT",
        "LV",
        "LT",
        "LU",
        "MY",
        "MT",
        "MX",
        "NL",
        "NZ",
        "NI",
        "NO",
        "PA",
        "PY",
        "PE",
        "PH",
        "PL",
        "PT",
        "SG",
        "SK",
        "ES",
        "SE",
        "CH",
        "TW",
        "TR",
        "UY",
        "US",
        "GB",
        "AD",
        "LI",
        "MC",
        "ID",
        "JP",
        "TH",
        "VN",
        "RO",
        "IL",
        "ZA",
        "SA",
        "AE",
        "BH",
        "QA",
        "OM",
        "KW",
        "EG",
        "MA",
        "DZ",
        "TN",
        "LB",
        "JO",
        "PS",
        "IN",
        "KZ",
        "MD",
        "UA",
        "AL",
        "BA",
        "HR",
        "ME",
        "MK",
        "RS",
        "SI",
        "KR",
        "BD",
        "PK",
        "LK",
        "GH",
        "KE",
        "NG",
        "TZ",
        "UG",
        "AG",
        "AM",
        "BS",
        "BB",
        "BZ",
        "BT",
        "BW",
        "BF",
        "CV",
        "CW",
        "DM",
        "FJ",
        "GM",
        "GE",
        "GD",
        "GW",
        "GY",
        "HT",
        "JM",
        "KI",
        "LS",
        "LR",
        "MW",
        "MV",
        "ML",
        "MH",
        "FM",
        "NA",
        "NR",
        "NE",
        "PW",
        "PG",
        "PR",
        "WS",
        "SM",
        "ST",
        "SN",
        "SC",
        "SL",
        "SB",
        "KN",
        "LC",
        "VC",
        "SR",
        "TL",
        "TO",
        "TT",
        "TV",
        "VU",
        "AZ",
        "BN",
        "BI",
        "KH",
        "CM",
        "TD",
        "KM",
        "GQ",
        "SZ",
        "GA",
        "GN",
        "KG",
        "LA",
        "MO",
        "MR",
        "MN",
        "NP",
        "RW",
        "TG",
        "UZ",
        "ZW",
        "BJ",
        "MG",
        "MU",
        "MZ",
        "AO",
        "CI",
        "DJ",
        "ZM",
        "CD",
        "CG",
        "IQ",
        "LY",
        "TJ",
        "VE",
        "ET",
        "XK"
      ],
      "disc_number": 2,
      "duration_ms": 186662,
      "explicit": false,
      "external_urls": {
        "spotify": "https://open.spotify.com/track/6XyGcm4JJq1KL6CWGk4joO"
      },
      "href": "https://api.spotify.com/v1/tracks/6XyGcm4JJq1KL6CWGk4joO",
      "id": "6XyGcm4JJq1KL6CWGk4joO",
      "name": "Punchline - Live from Holly’s Living Room",
      "preview_url": null,
      "track_number": 11,
      "type": "track",
      "uri": "spotify:track:6XyGcm4JJq1KL6CWGk4joO",
      "is_local": false
    },
    {
      "artists": [
        {
          "external_urls": {
            "spotify": "https://open.spotify.com/artist/6eUKZXaKkcviH0Ku9w2n3V"
          },
          "href": "https://api.spotify.com/v1/artists/6eUKZXaKkcviH0Ku9w2n3V",
          "id": "6eUKZXaKkcviH0Ku9w2n3V",
          "name": "Ed Sheeran",
          "type": "artist",
          "uri": "spotify:artist:6eUKZXaKkcviH0Ku9w2n3V"
        }
      ],
      "available_markets": [
        "AR",
        "AU",
        "AT",
        "BE",
        "BO",
        "BR",
        "BG",
        "CA",
        "CL",
        "CO",
        "CR",
        "CY",
        "CZ",
        "DK",
        "DO",
        "DE",
        "EC",
        "EE",
        "SV",
        "FI",
        "FR",
        "GR",
        "GT",
        "HN",
        "HK",
        "HU",
        "IS",
        "IE",
        "IT",
        "LV",
        "LT",
        "LU",
        "MY",
        "MT",
        "MX",
        "NL",
        "NZ",
        "NI",
        "NO",
        "PA",
        "PY",
        "PE",
        "PH",
        "PL",
        "PT",
        "SG",
        "SK",
        "ES",
        "SE",
        "CH",
        "TW",
        "TR",
        "UY",
        "US",
        "GB",
        "AD",
        "LI",
        "MC",
        "ID",
        "JP",
        "TH",
        "VN",
        "RO",
        "IL",
        "ZA",
        "SA",
        "AE",
        "BH",
        "QA",
        "OM",
        "KW",
        "EG",
        "MA",
        "DZ",
        "TN",
        "LB",
        "JO",
        "PS",
        "IN",
        "KZ",
        "MD",
        "UA",
        "AL",
        "BA",
        "HR",
        "ME",
        "MK",
        "RS",
        "SI",
        "KR",
        "BD",
        "PK",
        "LK",
        "GH",
        "KE",
        "NG",
        "TZ",
        "UG",
        "AG",
        "AM",
        "BS",
        "BB",
        "BZ",
        "BT",
        "BW",
        "BF",
        "CV",
        "CW",
        "DM",
        "FJ",
        "GM",
        "GE",
        "GD",
        "GW",
        "GY",
        "HT",
        "JM",
        "KI",
        "LS",
        "LR",
        "MW",
        "MV",
        "ML",
        "MH",
        "FM",
        "NA",
        "NR",
        "NE",
        "PW",
        "PG",
        "PR",
        "WS",
        "SM",
        "ST",
        "SN",
        "SC",
        "SL",
        "SB",
        "KN",
        "LC",
        "VC",
        "SR",
        "TL",
        "TO",
        "TT",
        "TV",
        "VU",
        "AZ",
        "BN",
        "BI",
        "KH",
        "CM",
        "TD",
        "KM",
        "GQ",
        "SZ",
        "GA",
        "GN",
        "KG",
        "LA",
        "MO",
        "MR",
        "MN",
        "NP",
        "RW",
        "TG",
        "UZ",
        "ZW",
        "BJ",
        "MG",
        "MU",
        "MZ",
        "AO",
        "CI",
        "DJ",
        "ZM",
        "CD",
        "CG",
        "IQ",
        "LY",
        "TJ",
        "VE",
        "ET",
        "XK"
      ],
      "disc_number": 2,
      "duration_ms": 166769,
      "explicit": false,
      "external_urls": {
        "spotify": "https://open.spotify.com/track/6r8VpUHx6dI2ZtZrVTZ7Vt"
      },
      "href": "https://api.spotify.com/v1/tracks/6r8VpUHx6dI2ZtZrVTZ7Vt",
      "id": "6r8VpUHx6dI2ZtZrVTZ7Vt",
      "name": "When Will I Be Alright - Live from Kristen’s Living Room",
      "preview_url": null,
      "track_number": 12,
      "type": "track",
      "uri": "spotify:track:6r8VpUHx6dI2ZtZrVTZ7Vt",
      "is_local": false
    },
    {
      "artists": [
        {
          "external_urls": {
            "spotify": "https://open.spotify.com/artist/6eUKZXaKkcviH0Ku9w2n3V"
          },
          "href": "https://api.spotify.com/v1/artists/6eUKZXaKkcviH0Ku9w2n3V",
          "id": "6eUKZXaKkcviH0Ku9w2n3V",
          "name": "Ed Sheeran",
          "type": "artist",
          "uri": "spotify:artist:6eUKZXaKkcviH0Ku9w2n3V"
        }
      ],
      "available_markets": [
        "AR",
        "AU",
        "AT",
        "BE",
        "BO",
        "BR",
        "BG",
        "CA",
        "CL",
        "CO",
        "CR",
        "CY",
        "CZ",
        "DK",
        "DO",
        "DE",
        "EC",
        "EE",
        "SV",
        "FI",
        "FR",
        "GR",
        "GT",
        "HN",
        "HK",
        "HU",
        "IS",
        "IE",
        "IT",
        "LV",
        "LT",
        "LU",
        "MY",
        "MT",
        "MX",
        "NL",
        "NZ",
        "NI",
        "NO",
        "PA",
        "PY",
        "PE",
        "PH",
        "PL",
        "PT",
        "SG",
        "SK",
        "ES",
        "SE",
        "CH",
        "TW",
        "TR",
        "UY",
        "US",
        "GB",
        "AD",
        "LI",
        "MC",
        "ID",
        "JP",
        "TH",
        "VN",
        "RO",
        "IL",
        "ZA",
        "SA",
        "AE",
        "BH",
        "QA",
        "OM",
        "KW",
        "EG",
        "MA",
        "DZ",
        "TN",
        "LB",
        "JO",
        "PS",
        "IN",
        "KZ",
        "MD",
        "UA",
        "AL",
        "BA",
        "HR",
        "ME",
        "MK",
        "RS",
        "SI",
        "KR",
        "BD",
        "PK",
        "LK",
        "GH",
        "KE",
        "NG",
        "TZ",
        "UG",
        "AG",
        "AM",
        "BS",
        "BB",
        "BZ",
        "BT",
        "BW",
        "BF",
        "CV",
        "CW",
        "DM",
        "FJ",
        "GM",
        "GE",
        "GD",
        "GW",
        "GY",
        "HT",
        "JM",
        "KI",
        "LS",
        "LR",
        "MW",
        "MV",
        "ML",
        "MH",
        "FM",
        "NA",
        "NR",
        "NE",
        "PW",
        "PG",
        "PR",
        "WS",
        "SM",
        "ST",
        "SN",
        "SC",
        "SL",
        "SB",
        "KN",
        "LC",
        "VC",
        "SR",
        "TL",
        "TO",
        "TT",
        "TV",
        "VU",
        "AZ",
        "BN",
        "BI",
        "KH",
        "CM",
        "TD",
        "KM",
        "GQ",
        "SZ",
        "GA",
        "GN",
        "KG",
        "LA",
        "MO",
        "MR",
        "MN",
        "NP",
        "RW",
        "TG",
        "UZ",
        "ZW",
        "BJ",
        "MG",
        "MU",
        "MZ",
        "AO",
        "CI",
        "DJ",
        "ZM",
        "CD",
        "CG",
        "IQ",
        "LY",
        "TJ",
        "VE",
        "ET",
        "XK"
      ],
      "disc_number": 2,
      "duration_ms": 214960,
      "explicit": true,
      "external_urls": {
        "spotify": "https://open.spotify.com/track/2eByhz5FCBvW0BoLl1I1vr"
      },
      "href": "https://api.spotify.com/v1/tracks/2eByhz5FCBvW0BoLl1I1vr",
      "id": "2eByhz5FCBvW0BoLl1I1vr",
      "name": "The Day I Was Born - Live from Danielle’s Living Room",
      "preview_url": null,
      "track_number": 13,
      "type": "track",
      "uri": "spotify:track:2eByhz5FCBvW0BoLl1I1vr",
      "is_local": false
    },
    {
      "artists": [
        {
          "external_urls": {
            "spotify": "https://open.spotify.com/artist/6eUKZXaKkcviH0Ku9w2n3V"
          },
          "href": "https://api.spotify.com/v1/artists/6eUKZXaKkcviH0Ku9w2n3V",
          "id": "6eUKZXaKkcviH0Ku9w2n3V",
          "name": "Ed Sheeran",
          "type": "artist",
          "uri": "spotify:artist:6eUKZXaKkcviH0Ku9w2n3V"
        }
      ],
      "available_markets": [
        "AR",
        "AU",
        "AT",
        "BE",
        "BO",
        "BR",
        "BG",
        "CA",
        "CL",
        "CO",
        "CR",
        "CY",
        "CZ",
        "DK",
        "DO",
        "DE",
        "EC",
        "EE",
        "SV",
        "FI",
        "FR",
        "GR",
        "GT",
        "HN",
        "HK",
        "HU",
        "IS",
        "IE",
        "IT",
        "LV",
        "LT",
        "LU",
        "MY",
        "MT",
        "MX",
        "NL",
        "NZ",
        "NI",
        "NO",
        "PA",
        "PY",
        "PE",
        "PH",
        "PL",
        "PT",
        "SG",
        "SK",
        "ES",
        "SE",
        "CH",
        "TW",
        "TR",
        "UY",
        "US",
        "GB",
        "AD",
        "LI",
        "MC",
        "ID",
        "JP",
        "TH",
        "VN",
        "RO",
        "IL",
        "ZA",
        "SA",
        "AE",
        "BH",
        "QA",
        "OM",
        "KW",
        "EG",
        "MA",
        "DZ",
        "TN",
        "LB",
        "JO",
        "PS",
        "IN",
        "KZ",
        "MD",
        "UA",
        "AL",
        "BA",
        "HR",
        "ME",
        "MK",
        "RS",
        "SI",
        "KR",
        "BD",
        "PK",
        "LK",
        "GH",
        "KE",
        "NG",
        "TZ",
        "UG",
        "AG",
        "AM",
        "BS",
        "BB",
        "BZ",
        "BT",
        "BW",
        "BF",
        "CV",
        "CW",
        "DM",
        "FJ",
        "GM",
        "GE",
        "GD",
        "GW",
        "GY",
        "HT",
        "JM",
        "KI",
        "LS",
        "LR",
        "MW",
        "MV",
        "ML",
        "MH",
        "FM",
        "NA",
        "NR",
        "NE",
        "PW",
        "PG",
        "PR",
        "WS",
        "SM",
        "ST",
        "SN",
        "SC",
        "SL",
        "SB",
        "KN",
        "LC",
        "VC",
        "SR",
        "TL",
        "TO",
        "TT",
        "TV",
        "VU",
        "AZ",
        "BN",
        "BI",
        "KH",
        "CM",
        "TD",
        "KM",
        "GQ",
        "SZ",
        "GA",
        "GN",
        "KG",
        "LA",
        "MO",
        "MR",
        "MN",
        "NP",
        "RW",
        "TG",
        "UZ",
        "ZW",
        "BJ",
        "MG",
        "MU",
        "MZ",
        "AO",
        "CI",
        "DJ",
        "ZM",
        "CD",
        "CG",
        "IQ",
        "LY",
        "TJ",
        "VE",
        "ET",
        "XK"
      ],
      "disc_number": 2,
      "duration_ms": 232902,
      "explicit": false,
      "external_urls": {
        "spotify": "https://open.spotify.com/track/09RjA5mm3ElFtMXy0f1I25"
      },
      "href": "https://api.spotify.com/v1/tracks/09RjA5mm3ElFtMXy0f1I25",
      "id": "09RjA5mm3ElFtMXy0f1I25",
      "name": "Head > Heels - Live from Keira’s Living Room",
      "preview_url": null,
      "track_number": 14,
      "type": "track",
      "uri": "spotify:track:09RjA5mm3ElFtMXy0f1I25",
      "is_local": false
    }
  ],
  "limit": 50,
  "next": null,
  "offset": 0,
  "previous": null,
  "total": 28
}